{"fx":{"mep":1424.91749174917,"cable":1474.55601092896},"local":[{"@odata.etag":"","ItemInternalId":"daeaba82-77c9-41c2-bc7b-5dd2522f3fdd","Link":"link","Empresa":"Loma Negra","Ticker":"LOC4O","Name":"ON LOMA NEGRA S.A CL 4","Vto":"46144","Cupon":"0.06","Fq":"S","Vt":"1","Vr":"1.02432876712329","Px":"1.07535522191058","TIR":"-0.363574153035879","Duration":"0.0958904109589041","Mduration":"0.150670202060964","Paridad":"1.04981452871873","Calificación":"AAA ","Monto Emitido":"10000000","Ley":"ARG","Segmento":"Industrials","CALL":"0","Paga":"CABLE","Amortización":"Bullet","Vol Total":"0"},{"@odata.etag":"","ItemInternalId":"576d23e3-a974-4e5e-b9ed-e5144493a805","Link":"link","Empresa":"Banco Galicia","Ticker":"BYCUO","Name":"ON BANCO GALICIA CL 28","Vto":"46171","Cupon":"0.059","Fq":"S","Vt":"1","Vr":"1.01988219178082","Px":"1.042","TIR":"-0.0745099180191755","Duration":"0.158904109589041","Mduration":"0.171697258223383","Paridad":"1.02168663047303","Calificación":"AAA","Monto Emitido":"31296051","Ley":"ARG","Segmento":"FINANCIALS","CALL":"Yes","Paga":"MEP","Amortización":"Bullet","Vol Total":"98790"},{"@odata.etag":"","ItemInternalId":"b558f2af-07e6-496b-a24f-5f46466e1240","Link":"link","Empresa":"John Deere","Ticker":"HJCBO","Name":"ON JOHN DEERE CLASE XI","Vto":"46172","Cupon":"0.06","Fq":"T","Vt":"1","Vr":"1","Px":"1.015","TIR":"0.0529302358627319","Duration":"1.90567456429416","Mduration":"1.80987733031782","Paridad":"1.015","Calificación":"A","Monto Emitido":"23898369","Ley":"ARG","Segmento":"AGRO","CALL":"-","Paga":"MEP","Amortización":"Bullet","Vol Total":"43000"},{"@odata.etag":"","ItemInternalId":"a6c00de4-eed2-4e7c-830e-c1d1a192f5c1","Link":"link","Empresa":"MercadoPago","Ticker":"SXC2O","Name":"ON MERCADO PAGO SERVICIOS DE PROCESAMIENTO CLASE 2","Vto":"46174","Cupon":"0.0498","Fq":"A","Vt":"1.02387671232877","Vr":"1","Px":"1.03514765489288","TIR":"-0.0148811674118042","Duration":"0.172602739726027","Mduration":"0.175210070111592","Paridad":"1.03514765489288","Calificación":" AA+","Monto Emitido":"50854527","Ley":"ARG","Segmento":"Utilities","CALL":"n/a","Paga":"MEP","Amortización":"Bullet","Vol Total":"214570"},{"@odata.etag":"","ItemInternalId":"d9bf8c54-c660-4a81-9b0c-89a0b1f43208","Link":"link","Empresa":"MSU","Ticker":"MSSEO","Name":"ON MSU SERIE 13","Vto":"46220","Cupon":"0.065","Fq":"A","Vt":"1","Vr":"1.04558904109589","Px":"1.03858645049218","TIR":"0.0877354669570923","Duration":"0.298630136986301","Mduration":"0.274542980401026","Paridad":"0.99330273144756","Calificación":"A+ ","Monto Emitido":"25000000","Ley":"ARG","Segmento":"AGRO","CALL":"0","Paga":"MEP","Amortización":"Bullet","Vol Total":"2604"},{"@odata.etag":"","ItemInternalId":"66bb271d-409a-47bd-971d-433199c08275","Link":"link","Empresa":"Cresud","Ticker":"CS45O","Name":"ON CRESUD CL 45","Vto":"46256","Cupon":"0.06","Fq":"S","Vt":"1","Vr":"1.02613698630137","Px":"1.02403705848292","TIR":"0.065718321800232","Duration":"0.392854170736125","Mduration":"0.368628522846926","Paridad":"0.997953559956921","Calificación":"AA+","Monto Emitido":"10199068","Ley":"ARG","Segmento":"Real Estate","CALL":"0","Paga":"CABLE","Amortización":"Bullet","Vol Total":"957"},{"@odata.etag":"","ItemInternalId":"f6ad6a89-c346-4dcb-8454-7cec2d9de6da","Link":"link","Empresa":"YPF LUZ","Ticker":"YFCNO","Name":"ON EF YPF ENERGIA ELECTRICA CLASE 22","Vto":"46298","Cupon":"0.06","Fq":"s","Vt":"1.0292602739726","Vr":"1","Px":"1.05","TIR":"0.0190064573287964","Duration":"0.503369464820252","Mduration":"0.493980642811405","Paridad":"1.05","Calificación":" AA+","Monto Emitido":"79946259","Ley":"ARG","Segmento":"Utilities","CALL":"n/a","Paga":"MEP","Amortización":"Bullet","Vol Total":"20326"},{"@odata.etag":"","ItemInternalId":"6b9685e7-326a-4cd8-a56c-637ffea2e2b1","Link":"link","Empresa":"John Deere","Ticker":"HJCFO","Name":"ON JOHN DEERE CLASE XIV","Vto":"46316","Cupon":"0.05","Fq":"S","Vt":"1","Vr":"1.02191780821918","Px":"0.989530978575565","TIR":"0.114001317024231","Duration":"0.549093614699579","Mduration":"0.492902123460986","Paridad":"0.968307794048475","Calificación":"A","Monto Emitido":"28658217","Ley":"ARG","Segmento":"AGRO","CALL":"0","Paga":"MEP","Amortización":"Bullet","Vol Total":"0"},{"@odata.etag":"","ItemInternalId":"9b6dead7-d0cb-4e87-aa9d-0916d472f198","Link":"link","Empresa":"Oiltanking","Ticker":"OTS5O","Name":"ON OILTANKING EBYTEM SA S5","Vto":"46318","Cupon":"0.0669","Fq":"S","Vt":"1.02895945205479","Vr":"1","Px":"1.045","TIR":"0.0383372259140015","Duration":"0.551158164708934","Mduration":"0.530808441567502","Paridad":"1.0155890962595","Calificación":"AA","Monto Emitido":"50000000","Ley":"ARG","Segmento":"O&G","CALL":"n/a","Paga":"MEP","Amortización":"Bullet","Vol Total":"25551"},{"@odata.etag":"","ItemInternalId":"92682479-7872-4841-a929-d7cd326f4d08","Link":"link","Empresa":"Edenor","Ticker":"DNC3O","Name":"ON EDENOR CL 3","Vto":"46348","Cupon":"0.0975","Fq":"S","Vt":"1","Vr":"1.03419178082192","Px":"1.058","TIR":"0.0599656534194946","Duration":"0.629087437831358","Mduration":"0.59349794571352","Paridad":"1.02302108720992","Calificación":"A","Monto Emitido":"95762688","Ley":"ARG","Segmento":"Utilities","CALL":"0","Paga":"MEP","Amortización":"Bullet","Vol Total":"261828"},{"@odata.etag":"","ItemInternalId":"c608abea-b8aa-4e04-8d27-8038574de5f5","Link":"link","Empresa":"YPF LUZ","Ticker":"YFCKO","Name":"ON EF YPF ENERGIA ELECTRICA CLASE 19","Vto":"46348","Cupon":"0.0525","Fq":"T","Vt":"1.00517808219178","Vr":"1","Px":"1.022","TIR":"0.0264160776138306","Duration":"0.642535674593533","Mduration":"0.625999230338708","Paridad":"1.022","Calificación":" AA+","Monto Emitido":"49018232","Ley":"ARG","Segmento":"Utilities","CALL":"n/a","Paga":"MEP","Amortización":"Bullet","Vol Total":"108000"},{"@odata.etag":"","ItemInternalId":"3821fafc-cac1-478f-9eae-d7913c6fdedd","Link":"link","Empresa":"Banco Galicia","Ticker":"BYCWO","Name":"ON BANCO GALICIA CL XXX","Vto":"46356","Cupon":"0.06","Fq":"S","Vt":"1.02235616438356","Vr":"1","Px":"1.052","TIR":"0.0154483270645142","Duration":"0.655764757032156","Mduration":"0.645788406513859","Paridad":"1.02899560510237","Calificación":"AAA","Monto Emitido":"144323518","Ley":"ARG","Segmento":"FINANCIALS","CALL":"Yes","Paga":"MEP","Amortización":"Bullet","Vol Total":"90000"},{"@odata.etag":"","ItemInternalId":"4deb6ddb-c8f7-4877-a122-85a60b503b04","Link":"link","Empresa":"Vista","Ticker":"VSCNO","Name":"ON VISTA OIL & GAS CL 22","Vto":"46361","Cupon":"0.05","Fq":"T","Vt":"1","Vr":"1.01575342465753","Px":"0.98066985645933","TIR":"0.106875777244568","Duration":"0.672420592149054","Mduration":"0.607494179539246","Paridad":"0.965460546480527","Calificación":"AAA ","Monto Emitido":"14668984","Ley":"ARG","Segmento":"O&G","CALL":"0","Paga":"CABLE","Amortización":"0","Vol Total":"0"},{"@odata.etag":"","ItemInternalId":"ff684cfc-c29a-47e1-9b82-a883472f4ec1","Link":"link","Empresa":"Banco Galicia","Ticker":"BYCXO","Name":"ON BANCO GALICIA CL XXXI","Vto":"46386","Cupon":"0.055","Fq":"S","Vt":"1.01476712328767","Vr":"1","Px":"1.05","TIR":"0.00799680233001709","Duration":"0.739782082963489","Mduration":"0.73391312477724","Paridad":"1.05","Calificación":"AAA","Monto Emitido":"71863952","Ley":"ARG","Segmento":"FINANCIALS","CALL":"Yes","Paga":"MEP","Amortización":"Bullet","Vol Total":"35000"},{"@odata.etag":"","ItemInternalId":"48877e10-bbac-4e01-ac75-4b5c837ef9cf","Link":"link","Empresa":"YPF","Ticker":"YM41O","Name":"ON YPF CL 41","Vto":"46395","Cupon":"0.06","Fq":"T","Vt":"1.01331506849315","Vr":"1","Px":"1.03","TIR":"0.0386739301681519","Duration":"0.756397107125487","Mduration":"0.728233457253551","Paridad":"1.03","Calificación":"AAA ","Monto Emitido":"99005943","Ley":"ARG","Segmento":"O&G","CALL":"0","Paga":"MEP","Amortización":"Bullet","Vol Total":"30675"},{"@odata.etag":"","ItemInternalId":"c0ff41fc-c570-44c5-b7ce-6984c9aa43ed","Link":"link","Empresa":"Cresud","Ticker":"CS44O","Name":"ON CRESUD CL 44","Vto":"46404","Cupon":"0.06","Fq":"S","Vt":"1","Vr":"1.01183561643836","Px":"1.02384875506659","TIR":"0.0448394250869751","Duration":"0.790941901194928","Mduration":"0.756998522647715","Paridad":"1.01187261886523","Calificación":"AA+","Monto Emitido":"39765830","Ley":"ARG","Segmento":"Real Estate","CALL":"0","Paga":"MEP","Amortización":"Bullet","Vol Total":"28346"},{"@odata.etag":"","ItemInternalId":"83640258-4e5a-4ff0-af18-acec619c7be8","Link":"link","Empresa":"YPF LUZ","Ticker":"YFCGO","Name":"ON YPF ENERGIA ELECTRICA CL 15","Vto":"46445","Cupon":"0.06","Fq":"T","Vt":"1","Vr":"1.00509589041096","Px":"1.029","TIR":"0.033571400642395","Duration":"0.89868414338787","Mduration":"0.869494011569313","Paridad":"1.02378291446328","Calificación":" AA+","Monto Emitido":"11287656","Ley":"ARG","Segmento":"Utilities","CALL":"0","Paga":"MEP","Amortización":"Bullet","Vol Total":"5201"},{"@odata.etag":"","ItemInternalId":"5e5e6e2c-61bf-459e-9880-8d59bc1fabdc","Link":"link","Empresa":"Irsa","Ticker":"IRCJO","Name":"ON IRSA CL 18","Vto":"46446","Cupon":"0.07","Fq":"S","Vt":"1","Vr":"1.00575342465753","Px":"1.029","TIR":"0.044171462059021","Duration":"0.903752892802859","Mduration":"0.865521540897826","Paridad":"1.02311359302642","Calificación":"AA+","Monto Emitido":"21408926","Ley":"ARG","Segmento":"Real Estate","CALL":"0","Paga":"MEP","Amortización":"Bullet","Vol Total":"87999"},{"@odata.etag":"","ItemInternalId":"b9fbf369-2191-4214-8288-1cfd7ec0e6af","Link":"link","Empresa":"Vista","Ticker":"VSCOO","Name":"ON VISTA OIL & GAS CL 23","Vto":"46452","Cupon":"0.0625","Fq":"S","Vt":"1","Vr":"1.0041095890411","Px":"1.01496914700544","TIR":"0.0507350397109985","Duration":"0.924581696523945","Mduration":"0.879938006805453","Paridad":"1.01081511229737","Calificación":"AAA ","Monto Emitido":"92202616","Ley":"ARG","Segmento":"O&G","CALL":"0","Paga":"CABLE","Amortización":"Bullet","Vol Total":"31840"},{"@odata.etag":"","ItemInternalId":"f72fa57b-44f6-462c-abd1-adbea076f90c","Link":"link","Empresa":"Genneia","Ticker":"GN43O","Name":"ON GENNEIA S.A. CL 43","Vto":"46454","Cupon":"0.0625","Fq":"T","Vt":"1","Vr":"1.00376712328767","Px":"1.015","TIR":"0.0520735120773315","Duration":"0.929458623542847","Mduration":"0.883454067489656","Paridad":"1.01119071989082","Calificación":"A+","Monto Emitido":"20697951","Ley":"ARG","Segmento":"Utilities","CALL":"0","Paga":"MEP","Amortización":"Bullet","Vol Total":"20"},{"@odata.etag":"","ItemInternalId":"2833050c-3ad0-4c64-ac5f-1da502c1e707","Link":"link","Empresa":"CGC","Ticker":"CP37O","Name":"ON CGC CIA GENERAL COMBUST CL 37","Vto":"46456","Cupon":"0.07","Fq":"t","Vt":"1","Vr":"1.00383561643836","Px":"0.9935","TIR":"0.0839592885971069","Duration":"0.919544556415829","Mduration":"0.848320196237196","Paridad":"0.989703875545851","Calificación":"AA- ","Monto Emitido":"27630742","Ley":"ARG","Segmento":"O&G","CALL":"0","Paga":"MEP","Amortización":"Bullet","Vol Total":"83491"},{"@odata.etag":"","ItemInternalId":"545a7464-c4ec-482a-ba4d-e3f612bed8ed","Link":"link","Empresa":"Aluar","Ticker":"LMS8O","Name":"ON ALUAR 8 USD CABLE ","Vto":"46467","Cupon":"0.0625","Fq":"T","Vt":"1","Vr":"1.00154109589041","Px":"0.996910248986682","TIR":"0.0730901384353638","Duration":"0.601973229124793","Mduration":"0.56097172787601","Paridad":"0.995376278694174","Calificación":"AAA","Monto Emitido":"100000000","Ley":"ARG","Segmento":"Industrials","CALL":"0","Paga":"CABLE","Amortización":"1","Vol Total":"37898"},{"@odata.etag":"","ItemInternalId":"64733014-4c2a-4e3c-acb1-9090959fd602","Link":"link","Empresa":"Vista","Ticker":"VSCWO","Name":"ON VISTA OIL & GAS CL 30","Vto":"46492","Cupon":"0.06","Fq":"T","Vt":"1.01216438356164","Vr":"1","Px":"1.034","TIR":"0.0391079473495484","Duration":"1.00817308840046","Mduration":"0.970229407803108","Paridad":"1.034","Calificación":"AAA ","Monto Emitido":"73256123","Ley":"ARG","Segmento":"O&G","CALL":"N/A","Paga":"MEP","Amortización":"Bullet","Vol Total":"35130"},{"@odata.etag":"","ItemInternalId":"6bfa319b-fd69-46a5-8fe4-f40c8bf800f7","Link":"link","Empresa":"Pan american","Ticker":"PN42O","Name":"ON PAN AMERICAN ENERGY CL 42","Vto":"46494","Cupon":"0.06","Fq":"S","Vt":"1.02695890410959","Vr":"1","Px":"1.0495","TIR":"0.0380151796340942","Duration":"1.01218539327653","Mduration":"0.975116176656811","Paridad":"1.0495","Calificación":"AAA ","Monto Emitido":"56135832","Ley":"ARG","Segmento":"O&G","CALL":"0","Paga":"MEP","Amortización":"Bullet","Vol Total":"490157"},{"@odata.etag":"","ItemInternalId":"7fcd6d8e-f7c1-4963-8669-df4652eeba6a","Link":"link","Empresa":"Oiltanking","Ticker":"OTS2O","Name":"ON OILTANKING EBYTEM SA S2","Vto":"46501","Cupon":"0.07","Fq":"T","Vt":"1","Vr":"1.01246575342466","Px":"1.03535819339896","TIR":"0.0484876012802124","Duration":"1.03235422496022","Mduration":"0.984612716163456","Paridad":"1.02261058203388","Calificación":"AA","Monto Emitido":"32947113","Ley":"ARG","Segmento":"O&G","CALL":"0","Paga":"MEP","Amortización":"Bullet","Vol Total":"13911"},{"@odata.etag":"","ItemInternalId":"135a2bf3-f6e7-4f5f-a2b4-87aecf165047","Link":"link","Empresa":"YPF","Ticker":"YM37O","Name":"ON YPF CL 37","Vto":"46514","Cupon":"0.07","Fq":"T","Vt":"1","Vr":"1.00978082191781","Px":"1.0415","TIR":"0.041074595451355","Duration":"1.06324919448639","Mduration":"1.0212997215876","Paridad":"1.03141194345715","Calificación":"AAA ","Monto Emitido":"139501701","Ley":"ARG","Segmento":"O&G","CALL":"0","Paga":"MEP","Amortización":"Bullet","Vol Total":"218967"},{"@odata.etag":"","ItemInternalId":"11fa35ff-58cc-4a03-a4ce-e37608e9d826","Link":"link","Empresa":"Arcor","Ticker":"RCCRO","Name":"ON ARCOR CL 26","Vto":"46516","Cupon":"0.0675","Fq":"S","Vt":"1","Vr":"1.02607534246575","Px":"1.062","TIR":"0.0343871068954468","Duration":"1.06537024068308","Mduration":"1.02995313222786","Paridad":"1.03501171507339","Calificación":"AAA ","Monto Emitido":"68415046","Ley":"ARG","Segmento":"Consumo","CALL":"0","Paga":"MEP","Amortización":"Bullet","Vol Total":"105707"},{"@odata.etag":"","ItemInternalId":"1db98d4c-5b2f-4dd7-a775-42ee517e6a2a","Link":"link","Empresa":"YPF LUZ","Ticker":"YFCMO","Name":"ON EF YPF ENERGIA ELECTRICA CLASE 21","Vto":"46527","Cupon":"0.065","Fq":"T","Vt":"1","Vr":"1.00676712328767","Px":"1.0445","TIR":"0.0315240240097046","Duration":"1.10176745354724","Mduration":"1.06809674607915","Paridad":"1.0374792500068","Calificación":" AA+","Monto Emitido":"53827026","Ley":"ARG","Segmento":"Utilities","CALL":"0","Paga":"MEP","Amortización":"Bullet","Vol Total":"42694"},{"@odata.etag":"","ItemInternalId":"cc446452-6a67-448d-9d61-c977c14fe972","Link":"link","Empresa":"Telecom","Ticker":"TLCQO","Name":"ON.TELECOM ARGENTINA C.  25","Vto":"46570","Cupon":"0.075","Fq":"T","Vt":"1.01808219178082","Vr":"1","Px":"1.06","TIR":"0.0411838579177856","Duration":"1.18981775711538","Mduration":"1.14275470952349","Paridad":"1.06","Calificación":"AA+","Monto Emitido":"50489739","Ley":"ARG","Segmento":"Utilities","CALL":"0","Paga":"MEP","Amortización":"Bullet","Vol Total":"51231"},{"@odata.etag":"","ItemInternalId":"7a8f2230-a074-4860-a31b-7f788a1e0053","Link":"link","Empresa":"Profertil","Ticker":"PFC2O","Name":"ON PROFERTIL S.A. CLASE 2","Vto":"46582","Cupon":"0.0725","Fq":"S","Vt":"1","Vr":"1.01489726027397","Px":"1.055","TIR":"0.0406341600418091","Duration":"1.24008129173641","Mduration":"1.19165922026487","Paridad":"1.03951408807154","Calificación":"AAA ","Monto Emitido":"54325110","Ley":"ARG","Segmento":"AGRO","CALL":"0","Paga":"MEP","Amortización":"Bullet","Vol Total":"0"},{"@odata.etag":"","ItemInternalId":"73c23300-5bfa-4674-92bc-b4b4db3f1d4b","Link":"link","Empresa":"YPF","Ticker":"YM38O","Name":"ON YPF CL 38","Vto":"46590","Cupon":"0.075","Fq":"T","Vt":"1.01376712328767","Vr":"1","Px":"1.059","TIR":"0.0400372648239136","Duration":"1.24731674610341","Mduration":"1.1993000523059","Paridad":"1.059","Calificación":"AAA ","Monto Emitido":"250000000","Ley":"ARG","Segmento":"O&G","CALL":"0","Paga":"MEP","Amortización":"Bullet","Vol Total":"126826"},{"@odata.etag":"","ItemInternalId":"0309b942-7c0b-44a6-8119-17a24756f7f8","Link":"link","Empresa":"Loma Negra","Ticker":"LOC5O","Name":"ON LOMA NEGRA S.A CL 5","Vto":"46592","Cupon":"0.08","Fq":"S","Vt":"1","Vr":"1.01424657534247","Px":"1.0625","TIR":"0.042171196937561","Duration":"1.26794265328963","Mduration":"1.21663567081446","Paridad":"1.047575634792","Calificación":"AAA","Monto Emitido":"112878134","Ley":"ARG","Segmento":"Industrials","CALL":"0","Paga":"MEP","Amortización":"Bullet","Vol Total":"399800"},{"@odata.etag":"","ItemInternalId":"5408a395-a05c-4178-a1db-13e634babaf0","Link":"link","Empresa":"Pan american","Ticker":"PN38O","Name":"ON PAN AMERICAN ENERGY CL 38","Vto":"46610","Cupon":"0.065","Fq":"S","Vt":"1","Vr":"1.0083698630137","Px":"1.02366474179178","TIR":"0.0538999605178833","Duration":"1.32107300100511","Mduration":"1.25350891972322","Paridad":"1.01516792532095","Calificación":"AAA ","Monto Emitido":"120000000","Ley":"ARG","Segmento":"O&G","CALL":"0","Paga":"CABLE","Amortización":"Bullet","Vol Total":"118075"},{"@odata.etag":"","ItemInternalId":"8d948a5c-677f-4fd9-97d3-a3b4800bf229","Link":"link","Empresa":"Scania","Ticker":"SBC1O","Name":"ON SCANIA CREDIT ARG CLASE 1","Vto":"46635","Cupon":"0.0875","Fq":"T","Vt":"0.865154109589041","Vr":"0.86","Px":"0.8849","TIR":"0.0595699644088745","Duration":"0.800407245873421","Mduration":"0.75540763966442","Paridad":"1.02895348837209","Calificación":"A+","Monto Emitido":"40000000","Ley":"ARG","Segmento":"Utilities","CALL":"0","Paga":"MEP","Amortización":"7 cuotas","Vol Total":"20460"},{"@odata.etag":"","ItemInternalId":"411ba2ae-4f05-40bb-a916-c16669409a42","Link":"link","Empresa":"Pan american","Ticker":"PN34O","Name":"ON PAN AMERICAN ENERGY CL 34","Vto":"46657","Cupon":"0.0497","Fq":"S","Vt":"1","Vr":"1.00040849315068","Px":"1.03","TIR":"0.0295443773269653","Duration":"1.46039246001756","Mduration":"1.41848422678896","Paridad":"1.02957942385727","Calificación":"AAA ","Monto Emitido":"23055471","Ley":"ARG","Segmento":"O&G","CALL":"0","Paga":"MEP","Amortización":"Bullet","Vol Total":"30188"},{"@odata.etag":"","ItemInternalId":"a76961e0-b113-4b32-b6e3-cadba7a55b7c","Link":"link","Empresa":"CGC","Ticker":"CP36O","Name":"ON CGC CIA GENERAL COMBUST CL 36","Vto":"46670","Cupon":"0.065","Fq":"S","Vt":"1","Vr":"1.03045205479452","Px":"0.99","TIR":"0.0959509992599487","Duration":"1.4390417211347","Mduration":"1.3130529760057","Paridad":"0.96074338965476","Calificación":"AA- ","Monto Emitido":"68262474","Ley":"ARG","Segmento":"O&G","CALL":"0","Paga":"MEP","Amortización":"Bullet","Vol Total":"15534"},{"@odata.etag":"","ItemInternalId":"5b7752ba-b589-4b41-9dfa-38c03c9c54de","Link":"link","Empresa":"Tecpetrol","Ticker":"TTCBO","Name":"ON TECPETROL CLASE 11","Vto":"46676","Cupon":"0.065","Fq":"S","Vt":"1.02938356164384","Vr":"1","Px":"1.079","TIR":"0.0320226144790649","Duration":"1.46364921569989","Mduration":"1.41823366577941","Paridad":"1.079","Calificación":"AAA","Monto Emitido":"114452024","Ley":"ARG","Segmento":"O&G","CALL":"-","Paga":"MEP","Amortización":"Bullet","Vol Total":"59825"},{"@odata.etag":"","ItemInternalId":"ef13bc77-8ad5-4552-8047-3b3acda637d9","Link":"link","Empresa":"Irsa","Ticker":"IRCNO","Name":"ON IRSA CL 22","Vto":"46683","Cupon":"0.0575","Fq":"S","Vt":"1","Vr":"1.01039726027397","Px":"1.0255","TIR":"0.0477819204330444","Duration":"1.51107071371289","Mduration":"1.44216146914271","Paridad":"1.01494732846161","Calificación":"AA+","Monto Emitido":"15799810","Ley":"ARG","Segmento":"Real Estate","CALL":"0","Paga":"MEP","Amortización":"Bullet","Vol Total":"64838"},{"@odata.etag":"","ItemInternalId":"ff86fce1-ba7d-4878-a21e-20ca34df6a03","Link":"link","Empresa":"Minera Exar","Ticker":"XMC1O","Name":"ON MINERA EXAR CLASE 1","Vto":"46702","Cupon":"0.08","Fq":"S","Vt":"1","Vr":"1","Px":"1.04006022003474","TIR":"0.064881386756897","Duration":"2.52470022429893","Mduration":"2.37087459288581","Paridad":"1.04006022003474","Calificación":"AA","Monto Emitido":"50000000","Ley":"ARG","Segmento":"Mineria","CALL":"0","Paga":"MEP","Amortización":"2 cuotas ","Vol Total":"40779"},{"@odata.etag":"","ItemInternalId":"6b291ca0-b46f-4ecd-a63b-eef7cdee3dde","Link":"link","Empresa":"John Deere","Ticker":"HJCHO","Name":"ON JOHN DEERE CLASE 16","Vto":"46769","Cupon":"0.07","Fq":"S","Vt":"1","Vr":"1.01380821917808","Px":"1.0285","TIR":"0.0639654302597046","Duration":"2.13985081157898","Mduration":"2.01120332552221","Paridad":"1.01449167657551","Calificación":"A","Monto Emitido":"50000000","Ley":"ARG","Segmento":"AGRO","CALL":"0","Paga":"MEP","Amortización":"Bullet","Vol Total":"11528"},{"@odata.etag":"","ItemInternalId":"098340ee-5d38-46d2-b136-b706a15d3bd5","Link":"link","Empresa":"Genneia","Ticker":"GN48O","Name":"ON GENNEIA S.A. CL 48","Vto":"46817","Cupon":"0.065","Fq":"S","Vt":"1.00445205479452","Vr":"1","Px":"1.009","TIR":"0.0633103513717651","Duration":"1.84454555113352","Mduration":"1.73471982921439","Paridad":"1.009","Calificación":"AA+","Monto Emitido":"27760264","Ley":"ARG","Segmento":"Utilities","CALL":"YES ","Paga":"MEP","Amortización":"Bullet","Vol Total":"384"},{"@odata.etag":"","ItemInternalId":"0f4dd25b-3933-44d4-afad-5da9fb662ecf","Link":"link","Empresa":"CGC","Ticker":"CP40O","Name":"ON CGC CIA GENERAL COMBUST CL 40","Vto":"46821","Cupon":"0.095","Fq":"t","Vt":"1.00546575342466","Vr":"1","Px":"1.0025","TIR":"0.100220866203308","Duration":"1.78944720710428","Mduration":"1.62644361879755","Paridad":"1.0025","Calificación":"AA- ","Monto Emitido":"55197497","Ley":"ARG","Segmento":"O&G","CALL":"n/a","Paga":"MEP","Amortización":"Bullet","Vol Total":"198418"},{"@odata.etag":"","ItemInternalId":"d3335993-5cd0-48e6-a8e3-e048d039ffb0","Link":"link","Empresa":"Pluspetrol","Ticker":"PLC3O","Name":"ON PLUSPETROL C3 USD 7,25%","Vto":"46873","Cupon":"0.0725","Fq":"S","Vt":"1","Vr":"1.01171917808219","Px":"1.0565","TIR":"0.0502022314071655","Duration":"1.95825820853175","Mduration":"1.86464868381386","Paridad":"1.04426210641049","Calificación":"A+","Monto Emitido":"90722914","Ley":"ARG","Segmento":"O&G","CALL":"0","Paga":"MEP","Amortización":"Bullet","Vol Total":"81155"},{"@odata.etag":"","ItemInternalId":"42f0d684-4980-4e49-8b71-83b8e487ff53","Link":"link","Empresa":"Oleoductos del valle","Ticker":"OLC2O","Name":"ON OLEDUCTOS DEL VALLE CLASE 2","Vto":"46913","Cupon":"0.01","Fq":"T","Vt":"1","Vr":"1.01304109589041","Px":"0.860296881818182","TIR":"0.0827214002609253","Duration":"2.17255045670003","Mduration":"2.00656462149586","Paridad":"0.849222095044451","Calificación":"AAA ","Monto Emitido":"43324070","Ley":"ARG","Segmento":"O&G","CALL":"0","Paga":"MEP","Amortización":"Bullet","Vol Total":"0"},{"@odata.etag":"","ItemInternalId":"3b7d1a44-0ec1-4c8c-9334-be5b6e637894","Link":"link","Empresa":"Oleoductos del valle","Ticker":"OLC5O","Name":"ON OLEDUCTOS DEL VALLE CLASE 5","Vto":"46916","Cupon":"0.0789","Fq":"s","Vt":"1","Vr":"1.02334575342466","Px":"1.0825","TIR":"0.0501542101583143","Duration":"2.02976173608916","Mduration":"1.93282254782673","Paridad":"1.05780475110917","Calificación":"AAA ","Monto Emitido":"85000000","Ley":"ARG","Segmento":"O&G","CALL":"0","Paga":"MEP","Amortización":"Bullet","Vol Total":"45696"},{"@odata.etag":"","ItemInternalId":"6a91ac83-3164-4439-8b55-5916fc5edf27","Link":"link","Empresa":"Edenor","Ticker":"DNC5O","Name":"ON EDENOR CL 5","Vto":"46970","Cupon":"0.095","Fq":"S","Vt":"1","Vr":"1.01379452054795","Px":"1.0545","TIR":"0.0723518514633179","Duration":"1.72594865063981","Mduration":"1.60949845732499","Paridad":"1.04015160728039","Calificación":"A","Monto Emitido":"81920187","Ley":"ARG","Segmento":"Utilities","CALL":"0","Paga":"MEP","Amortización":"Bullet","Vol Total":"194627"},{"@odata.etag":"","ItemInternalId":"fa6cbfc2-b724-4141-b38c-80f794f31680","Link":"link","Empresa":"YPF","Ticker":"YM40O","Name":"ON YPF CL 40","Vto":"46993","Cupon":"0.075","Fq":"T","Vt":"1","Vr":"1.00616438356164","Px":"1.052","TIR":"0.0557317972183227","Duration":"2.22525893880954","Mduration":"2.10778811879374","Paridad":"1.04555479918312","Calificación":"AAA ","Monto Emitido":"51383412","Ley":"ARG","Segmento":"O&G","CALL":"0","Paga":"MEP","Amortización":"Bullet","Vol Total":"60959"},{"@odata.etag":"","ItemInternalId":"2cd7ae6a-0f50-4748-86f7-b0c138fcc130","Link":"link","Empresa":"Pampa","Ticker":"MGCNO","Name":"ON PAMPA CL 22","Vto":"47030","Cupon":"0.0575","Fq":"S","Vt":"1","Vr":"1.02788356164384","Px":"1.048","TIR":"0.0495040464401245","Duration":"2.31827735662093","Mduration":"2.20892655391319","Paridad":"1.01957073651805","Calificación":"AA+","Monto Emitido":"83977835","Ley":"ARG","Segmento":"Energia","CALL":"0","Paga":"MEP","Amortización":"Bullet","Vol Total":"140578"},{"@odata.etag":"","ItemInternalId":"6820edaf-8864-45eb-ae28-55e082215420","Link":"link","Empresa":"YPF","Ticker":"YMCZO","Name":"ON YPF CL XXXIII","Vto":"47036","Cupon":"0.07","Fq":"S","Vt":"1","Vr":"1.03279452054795","Px":"1.04347137436067","TIR":"0.0663991022109985","Duration":"2.29357806327093","Mduration":"2.15076893680385","Paridad":"1.01033782964598","Calificación":"AAA ","Monto Emitido":"25000000","Ley":"ARG","Segmento":"O&G","CALL":"0","Paga":"CABLE","Amortización":"Bullet","Vol Total":"30573"},{"@odata.etag":"","ItemInternalId":"0ea03ce7-86ac-4f33-9c64-15bd3297c128","Link":"link","Empresa":"YPF","Ticker":"YMCYO","Name":"ON YPF CL 32","Vto":"47036","Cupon":"0.065","Fq":"T","Vt":"1","Vr":"1.01406849315068","Px":"1.04","TIR":"0.0550720643997192","Duration":"2.32837813902286","Mduration":"2.20684275281953","Paridad":"1.02557175084766","Calificación":"AAA ","Monto Emitido":"125000000","Ley":"ARG","Segmento":"O&G","CALL":"0","Paga":"MEP","Amortización":"Bullet","Vol Total":"41934"},{"@odata.etag":"","ItemInternalId":"3c2eb30f-4239-4d21-8d09-80c79a661d4e","Link":"link","Empresa":"Aluar","Ticker":"LMS7O","Name":"ON ALUAR ALUMINIO ARGENTINO SERIE 7","Vto":"47038","Cupon":"0.07","Fq":"T","Vt":"1","Vr":"0.930237021917808","Px":"0.929093225246092","TIR":"0.0729016733169556","Duration":"1.22112949177772","Mduration":"1.13815601387078","Paridad":"0.998770424478098","Calificación":"AAA","Monto Emitido":"137898136","Ley":"ARG","Segmento":"Industrials","CALL":"0","Paga":"Cable","Amortización":"12 cuotas","Vol Total":"7892"},{"@odata.etag":"","ItemInternalId":"df3f5a59-71ed-486f-b1ee-5048b6ea9b73","Link":"link","Empresa":"PCR","Ticker":"PQCRO","Name":"ON PCR CLASE R","Vto":"47048","Cupon":"0.0675","Fq":"S","Vt":"1","Vr":"1.02940410958904","Px":"1.01760277938622","TIR":"0.0738269376754761","Duration":"2.33282444311554","Mduration":"2.17243986090107","Paridad":"0.98853576540749","Calificación":"A+","Monto Emitido":"46018072","Ley":"ARG","Segmento":"O&G","CALL":"0","Paga":"MEP","Amortización":"Bullet","Vol Total":"24944"},{"@odata.etag":"","ItemInternalId":"700e6cc4-a98f-40d5-8428-86e4f0ee3477","Link":"link","Empresa":"Pan american","Ticker":"PN37O","Name":"ON PAN AMERICAN ENERGY CL 37","Vto":"47070","Cupon":"0.0625","Fq":"S","Vt":"1","Vr":"1.02345890410959","Px":"1.05269253039954","TIR":"0.0510793733596802","Duration":"2.41317643495051","Mduration":"2.29590314120333","Paridad":"1.02856355655568","Calificación":"AAA ","Monto Emitido":"74172648","Ley":"ARG","Segmento":"O&G","CALL":"0","Paga":"MEP","Amortización":"Bullet","Vol Total":"11462"},{"@odata.etag":"","ItemInternalId":"31e458ef-ccbb-452b-b32a-961edb2a0212","Link":"link","Empresa":"Scania","Ticker":"SBC2O","Name":"ON SCANIA CREDIT ARG CLASE 2","Vto":"47134","Cupon":"0.0749","Fq":"T","Vt":"1.01498","Vr":"1","Px":"1.019","TIR":"0.0737457799911499","Duration":"1.45396784878441","Mduration":"1.35410809139236","Paridad":"1.019","Calificación":"A+","Monto Emitido":"40979825","Ley":"ARG","Segmento":"Utilities","CALL":"0","Paga":"MEP","Amortización":"11 cuotas","Vol Total":"43973"},{"@odata.etag":"","ItemInternalId":"fbe470e4-9ac2-4a0c-b6b7-92b6d5b2c312","Link":"link","Empresa":"Loma Negra","Ticker":"LOC6O","Name":"ON LOMA NEGRA S.A CL 6","Vto":"47141","Cupon":"0.065","Fq":"S","Vt":"1.01175342465753","Vr":"1","Px":"1.0265","TIR":"0.0600740194320679","Duration":"2.59752377563389","Mduration":"2.45032302275034","Paridad":"1.0265","Calificación":"AAA","Monto Emitido":"60000000","Ley":"ARG","Segmento":"Industrials","CALL":"n/a","Paga":"MEP","Amortización":"Bullet","Vol Total":"172447"},{"@odata.etag":"","ItemInternalId":"fe27bb77-7214-4ae5-968d-3323ff401e42","Link":"link","Empresa":"Pluspetrol","Ticker":"PLC6O","Name":"ON PLUSPETROL CLASE 6","Vto":"47176","Cupon":"0.065","Fq":"S","Vt":"1.00552054794521","Vr":"1","Px":"1.023","TIR":"0.0591256856918335","Duration":"2.698520995474","Mduration":"2.54787607545491","Paridad":"1.023","Calificación":"A+","Monto Emitido":"167492889","Ley":"ARG","Segmento":"O&G","CALL":"n/a","Paga":"MEP","Amortización":"Bullet","Vol Total":"257664"},{"@odata.etag":"","ItemInternalId":"0bc86293-8eae-4cfb-86b6-9756db27db95","Link":"link","Empresa":"YPF","Ticker":"YM42O","Name":"ON YPF CL 42","Vto":"47179","Cupon":"0.07","Fq":"S","Vt":"1","Vr":"1.0226301369863","Px":"1.054","TIR":"0.0573476457595825","Duration":"2.86924368588389","Mduration":"2.71362375221697","Paridad":"1.03067566843487","Calificación":"AAA ","Monto Emitido":"355922807","Ley":"ARG","Segmento":"O&G","CALL":"02/09/27-01/03/28 @101 / 02/03/28-01/03/29 @100","Paga":"MEP","Amortización":"Bullet","Vol Total":"556112"},{"@odata.etag":"","ItemInternalId":"4e602634-985d-4091-9a4f-0de3d05f54c5","Link":"link","Empresa":"Telecom","Ticker":"TLCUO","Name":"ON.TELECOM ARGENTINA C.  28","Vto":"47182","Cupon":"0.065","Fq":"S","Vt":"1.0046301369863","Vr":"1","Px":"1.022","TIR":"0.0592907667160034","Duration":"2.70742636505151","Mduration":"2.55588592870023","Paridad":"1.022","Calificación":"AA+","Monto Emitido":"81329886","Ley":"ARG","Segmento":"Utilities","CALL":"0","Paga":"MEP","Amortización":"Bullet","Vol Total":"173718"},{"@odata.etag":"","ItemInternalId":"2e8365d3-832b-44f9-ada6-6ae16906d493","Link":"link","Empresa":"Vista","Ticker":"VSCPO","Name":"ON VISTA OIL & GAS CL 24","Vto":"47241","Cupon":"0.08","Fq":"S","Vt":"1","Vr":"1.03221917808219","Px":"1.04636990595611","TIR":"0.07458336353302","Duration":"2.11354151179843","Mduration":"1.96684741595991","Paridad":"1.01370903406408","Calificación":"AAA ","Monto Emitido":"46561789","Ley":"ARG","Segmento":"O&G","CALL":"0","Paga":"CABLE","Amortización":"Amort","Vol Total":"27973"},{"@odata.etag":"","ItemInternalId":"13d277fc-fbb2-4bef-a2fb-4af29da3eb63","Link":"link","Empresa":"CEPU","Ticker":"NPCCO","Name":"ON.CENTRAL PUERTO SA CL C","Vto":"47355","Cupon":"0.08","Fq":"S","Vt":"1.00723287671233","Vr":"1","Px":"1.03574195677281","TIR":"0.0715433645248413","Duration":"3.04030996320388","Mduration":"2.83731864137114","Paridad":"1.03574195677281","Calificación":"AA-","Monto Emitido":"89067309","Ley":"ARG","Segmento":"Utilities","CALL":"-","Paga":"CABLE","Amortización":"Bullet","Vol Total":"79800"},{"@odata.etag":"","ItemInternalId":"1179927e-d99a-4a6c-8917-f8ea7f4f7005","Link":"link","Empresa":"Pan american","Ticker":"PN41O","Name":"ON PAN AMERICAN ENERGY CL 41","Vto":"47357","Cupon":"0.075","Fq":"S","Vt":"1","Vr":"1.0063698630137","Px":"1.05620150550087","TIR":"0.0595083475112915","Duration":"3.06719494451402","Mduration":"2.89492286844048","Paridad":"1.04951623087951","Calificación":"AAA ","Monto Emitido":"85939129","Ley":"ARG","Segmento":"O&G","CALL":"0","Paga":"MEP","Amortización":"Bullet","Vol Total":"71666"},{"@odata.etag":"","ItemInternalId":"47b227f7-5434-4f1e-92c6-d1ce32d69d6f","Link":"link","Empresa":"Pan american","Ticker":"PN35O","Name":"ON PAN AMERICAN ENERGY CL 35","Vto":"47388","Cupon":"0.07","Fq":"S","Vt":"1","Vr":"1.00057534246575","Px":"1.04006022003474","TIR":"0.0581964731216431","Duration":"3.16958197515418","Mduration":"2.99526794471732","Paridad":"1.0394621733049","Calificación":"AAA ","Monto Emitido":"176944529","Ley":"ARG","Segmento":"O&G","CALL":"0","Paga":"MEP","Amortización":"Bullet","Vol Total":"623801"},{"@odata.etag":"","ItemInternalId":"418b4f23-ab48-4754-bda3-e04c50f78d09","Link":"link","Empresa":"Irsa","Ticker":"IRCOO","Name":"ON IRSA CL 23","Vto":"47414","Cupon":"0.0725","Fq":"S","Vt":"1.03138356164384","Vr":"1","Px":"1.056","TIR":"0.0655713987350464","Duration":"3.12513691674719","Mduration":"2.9328273266879","Paridad":"1.056","Calificación":"AA+ ","Monto Emitido":"MEP","Ley":"ARG","Segmento":"Real Estate","CALL":"0","Paga":"MEP","Amortización":"Bullet","Vol Total":"58923"},{"@odata.etag":"","ItemInternalId":"6a61c5f9-c82d-440f-b0c6-0d833f2f3ba2","Link":"link","Empresa":"Tecpetrol","Ticker":"TTC9O","Name":"ON TECPETROL CLASE 9","Vto":"47415","Cupon":"0.068","Fq":"S","Vt":"1.02924931506849","Vr":"1","Px":"1.065","TIR":"0.0575824880599975","Duration":"3.15106430810386","Mduration":"2.97949743275732","Paridad":"1.065","Calificación":"AAA","Monto Emitido":"80541942","Ley":"ARG","Segmento":"O&G","CALL":"-","Paga":"MEP","Amortización":"Bullet","Vol Total":"142179"},{"@odata.etag":"","ItemInternalId":"b8cdd0c9-08ff-49af-b495-49f1aa098479","Link":"link","Empresa":"Pluspetrol","Ticker":"PLC2O","Name":"ON PLUSPETROL C2 USD 7,5%","Vto":"47510","Cupon":"0.075","Fq":"S","Vt":"1","Vr":"1.03164383561644","Px":"1.0835","TIR":"0.0605234384536743","Duration":"3.31624504471775","Mduration":"3.12698892308603","Paridad":"1.05026556898154","Calificación":"A+","Monto Emitido":"123020337","Ley":"ARG","Segmento":"O&G","CALL":"0","Paga":"MEP","Amortización":"Bullet","Vol Total":"61117"},{"@odata.etag":"","ItemInternalId":"57117577-c909-400c-bdd9-284ef0ec3d9c","Link":"link","Empresa":"Oleoductos del valle","Ticker":"OLC7O","Name":"ON OLEDUCTOS DEL VALLE CLASE 7","Vto":"47537","Cupon":"0.069","Fq":"s","Vt":"1.00661643835616","Vr":"1","Px":"1.02812970469021","TIR":"0.0464745283126831","Duration":"3.51390313150583","Mduration":"3.35784869715997","Paridad":"1.02812970469021","Calificación":"AAA ","Monto Emitido":"110000000","Ley":"ARG","Segmento":"O&G","CALL":"0","Paga":"MEP","Amortización":"Bullet","Vol Total":"126234"},{"@odata.etag":"","ItemInternalId":"834c6198-ba22-46b9-9950-e3fff91d331c","Link":"link","Empresa":"Vista","Ticker":"VSCUO","Name":"ON VISTA OIL & GAS CL 28","Vto":"47549","Cupon":"0.075","Fq":"S","Vt":"1.00472602739726","Vr":"1","Px":"1.02749572669369","TIR":"0.0694531583786011","Duration":"3.47452674231182","Mduration":"3.2488816504872","Paridad":"1.02266259525038","Calificación":"AAA ","Monto Emitido":"92413570","Ley":"ARG","Segmento":"O&G","CALL":"N/A","Paga":"CABLE","Amortización":"Bullet","Vol Total":"259300"},{"@odata.etag":"","ItemInternalId":"9b955e06-c27a-416a-bb52-7e97eeb510b1","Link":"link","Empresa":"YPF","Ticker":"YM39O","Name":"ON YPF CL 39","Vto":"47686","Cupon":"0.0875","Fq":"s","Vt":"1","Vr":"1.01606164383562","Px":"1.07150897510133","TIR":"0.0735606813430786","Duration":"3.65288673835488","Mduration":"3.40258990650154","Paridad":"1.05457083396673","Calificación":"AAA ","Monto Emitido":"224801688","Ley":"ARG","Segmento":"O&G","CALL":"0","Paga":"CABLE","Amortización":"Bullet","Vol Total":"187188"},{"@odata.etag":"","ItemInternalId":"369b5722-0ab3-4926-86bd-dea0e8e665be","Link":"link","Empresa":"Vista","Ticker":"VSCRO","Name":"ON VISTA OIL & GAS CL 26","Vto":"48131","Cupon":"0.0765","Fq":"S","Vt":"1","Vr":"1.0358397260274","Px":"1.108","TIR":"0.0589634370803833","Duration":"3.81199989976643","Mduration":"3.59974647498342","Paridad":"1.06966355137715","Calificación":"AAA ","Monto Emitido":"150000000","Ley":"ARG","Segmento":"O&G","CALL":"0","Paga":"MEP","Amortización":"Bullet","Vol Total":"157469"},{"@odata.etag":"","ItemInternalId":"7a01fc5f-7958-4c93-a793-66917dce1c05","Link":"link","Empresa":"Pan american","Ticker":"PN36O","Name":"ON PAN AMERICAN ENERGY CL 36","Vto":"48165","Cupon":"0.0725","Fq":"S","Vt":"1","Vr":"1.02721232876712","Px":"1.0785","TIR":"0.0624976110458374","Duration":"4.62872748030612","Mduration":"4.3564591884117","Paridad":"1.0499289872177","Calificación":"AAA ","Monto Emitido":"78100553","Ley":"ARG","Segmento":"O&G","CALL":"0","Paga":"MEP","Amortización":"Bullet","Vol Total":"99925"}],"ny":[{"@odata.etag":"","ItemInternalId":"55355dcb-9790-48dd-8add-3302c64ef028","Link":"link","Empresa":"Aluar","TiCKER BBG":"","Ticker":"LMS9O","Name":"ON ALUAR 9 USD CABLE ","Vto":"46186","Cupon":"0.06","Fq":"T","Vt":"1.00279452054795","Vr":"1","Px":"1.04343272727273","TIR":"-0.122747908756137","Duration":"0.208333333333333","Mduration":"0.237483997374045","Paridad":"1.04343272727273","Calificación":"AAA","Monto Emitido":"50000000","Ley":"NY","Segmento":"Industrials","CALL":"101","Paga":"CABLE","Amortización":"Bullet","volumen total":"7761"},{"@odata.etag":"","ItemInternalId":"f42e3646-b9b8-415e-8a83-69ff6f4489a6","Link":"link","Empresa":"Banco Galicia","TiCKER BBG":"GALIAR 26","Ticker":"BYC2O","Name":"ON BANCO GALICIA CL 12","Vto":"46222","Cupon":"0.0825","Fq":"S","Vt":"1.01582191780822","Vr":"1","Px":"0.88690059808315","TIR":"0.686872892379761","Duration":"0.311111111111111","Mduration":"0.184430677922751","Paridad":"0.873086692199716","Calificación":"CCC","Monto Emitido":"250000000","Ley":"NY","Segmento":"FINANCIALS","CALL":"Yes","Paga":"CABLE","Amortización":"Bullet","volumen total":"200000"},{"@odata.etag":"","ItemInternalId":"11c1d58f-a31f-4d3e-acab-80939d2d126b","Link":"link","Empresa":"Banco Macro","TiCKER BBG":"BMAAR 26","Ticker":"BACAO","Name":"ON BANCO MACRO CL A","Vto":"46330","Cupon":"0.0675","Fq":"S","Vt":"1.027","Vr":"1","Px":"0.954","TIR":"0.21254237651825","Duration":"0.590596218678135","Mduration":"0.487072641843661","Paridad":"0.928919182083739","Calificación":"CCC+","Monto Emitido":"400000000","Ley":"NY","Segmento":"FINANCIALS","CALL":"Yes","Paga":"CABLE","Amortización":"Bullet","volumen total":"0"},{"@odata.etag":"","ItemInternalId":"173d5f91-c0e7-41e9-a24c-c93c5ae7beb7","Link":"link","Empresa":"PAE","TiCKER BBG":"PANAME 27","Ticker":"PNDCO","Name":"ON.PAN AMERCIAN ENERGY C12","Vto":"46507","Cupon":"0.09125","Fq":"S","Vt":"0.62265","Vr":"0.6","Px":"0.635","TIR":"0.0555085039138794","Duration":"0.570148872754437","Mduration":"0.540165115335685","Paridad":"1.01983457801333","Calificación":"AAA ","Monto Emitido":"300000000","Ley":"NY","Segmento":"O&G","CALL":"0","Paga":"CABLE","Amortización":"5 Cuotas","volumen total":"143000"},{"@odata.etag":"","ItemInternalId":"5f2e99ee-95cb-4c9c-b971-9a67c7eb43b9","Link":"link","Empresa":"YPF","TiCKER BBG":"YPFDAR 27","Ticker":"YCAMO","Name":"ON YPF CLASE 53","Vto":"46589","Cupon":"0.0695","Fq":"S","Vt":"1","Vr":"0","Px":"1.02414783039102","TIR":"0.0612943029403687","Duration":"1.27786183732689","Mduration":"1.20405982938617","Paridad":"1.01105672333762","Calificación":"B2","Monto Emitido":"809303000","Ley":"NY","Segmento":"O&G","CALL":"Yes","Paga":"CABLE","Amortización":"Bullet","volumen total":"127000"},{"@odata.etag":"","ItemInternalId":"b5c57314-e442-4c75-a883-3c09c11b2a4c","Link":"link","Empresa":"Irsa","TiCKER BBG":"IRSAAR 28","Ticker":"IRCFO","Name":"ON IRSA CL 14","Vto":"46926","Cupon":"0.0875","Fq":"S","Vt":"0.65","Vr":"0.665270547945205","Px":"0.671010064345818","TIR":"0.0821576833724975","Duration":"1.33622837864122","Mduration":"1.23478158421139","Paridad":"1.008627341791","Calificación":"AA+ ","Monto Emitido":"171202815","Ley":"NY","Segmento":"Real Estate","CALL":"","Paga":"CABLE","Amortización":"5 cuotas","volumen total":"220621"},{"@odata.etag":"","ItemInternalId":"1dbec433-8f94-4cbc-9f73-60a5a53ec3ff","Link":"link","Empresa":"Banco Galicia","TiCKER BBG":"GALIAR 28","Ticker":"BYCHO","Name":"ON BANCO GALICIA CL 16","Vto":"47036","Cupon":"0.0775","Fq":"S","Vt":"1","Vr":"1.03630821917808","Px":"1.06279491833031","TIR":"0.0670355081558228","Duration":"2.30392640696056","Mduration":"2.15918438454075","Paridad":"1.02555870798095","Calificación":"CCC","Monto Emitido":"325000000","Ley":"NY","Segmento":"FINANCIALS","CALL":"Yes","Paga":"CABLE","Amortización":"Bullet","volumen total":"62000"},{"@odata.etag":"","ItemInternalId":"f52daabb-51ce-41c3-9f06-c8cfa32fb905","Link":"link","Empresa":"Banco Macro","TiCKER BBG":"BMAAR 29","Ticker":"BACGO","Name":"ON BANCO MACRO CL G","Vto":"47292","Cupon":"0.08","Fq":"S","Vt":"1","Vr":"1.0212602739726","Px":"1.04250519716218","TIR":"0.0736456346511841","Duration":"2.90500661574877","Mduration":"2.70574062986115","Paridad":"1.02080265308562","Calificación":"CCC+","Monto Emitido":"400000000","Ley":"NY","Segmento":"FINANCIALS","CALL":"Yes","Paga":"CABLE","Amortización":"Bullet","volumen total":"108000"},{"@odata.etag":"","ItemInternalId":"614e0966-f187-477a-8ff7-5e4163aa4e73","Link":"link","Empresa":"YPF","TiCKER BBG":"YPFDAR 29","Ticker":"YMCIO","Name":"ON YPF CLASE 17","Vto":"47299","Cupon":"Step Up","Fq":"S","Vt":"1.02219178082192","Vr":"1","Px":"1.05120079194852","TIR":"0.0728574800491333","Duration":"1.63035578751974","Mduration":"1.51963873845114","Paridad":"1.0283792255728","Calificación":"B2","Monto Emitido":"747833257","Ley":"NY","Segmento":"O&G","CALL":"Yes","Paga":"CABLE","Amortización":"7 cuotas","volumen total":"421829"},{"@odata.etag":"","ItemInternalId":"927adc47-6505-4e73-8fb1-733f045e4cec","Link":"link","Empresa":"Edenor","TiCKER BBG":"EDNAR 30","Ticker":"DNC7O","Name":"ON EDENOR CL7","Vto":"47780","Cupon":"0.0975","Fq":"S","Vt":"1.04193835616438","Vr":"1","Px":"1.04830226035308","TIR":"0.0961045217514038","Duration":"2.8766897923203","Mduration":"2.62446667743309","Paridad":"1.04830226035308","Calificación":"B-","Monto Emitido":"385000000","Ley":"NY","Segmento":"Utilities","CALL":"-","Paga":"CABLE","Amortización":"3 cuotas","volumen total":"362000"},{"@odata.etag":"","ItemInternalId":"63bf2d5b-9fe8-4ba4-9c8e-c76c07f882f9","Link":"link","Empresa":"Tecpetrol","TiCKER BBG":"TECPETROL 30","Ticker":"TTCDO","Name":"ON.TECPETROL CLASE XII","Vto":"47790","Cupon":"0.07625","Fq":"S","Vt":"1.03070890410959","Vr":"1","Px":"1.0475","TIR":"0.0730830240249634","Duration":"3.91035838214782","Mduration":"3.64404085667173","Paridad":"1.01629082258188","Calificación":"B1","Monto Emitido":"750000000","Ley":"NY","Segmento":"O&G","CALL":"YES","Paga":"CABLE","Amortización":"Bullet","volumen total":"423000"},{"@odata.etag":"","ItemInternalId":"cb429744-64a5-4269-b5df-d9e26a302032","Link":"link","Empresa":"Pluspetrol","TiCKER BBG":"PLUSPE 32","Ticker":"PLC5O","Name":"ON PLUSPETROL Clase 5","Vto":"47986","Cupon":"0.08125","Fq":"S","Vt":"1","Vr":"1","Px":"1.05116386797915","TIR":"0.0710681867599487","Duration":"4.63280115576465","Mduration":"4.32540263358879","Paridad":"1.05116386797915","Calificación":"BB","Monto Emitido":"500000000","Ley":"NY","Segmento":"O&G","CALL":"yes","Paga":"CABLE","Amortización":"Bullet","volumen total":"490000"},{"@odata.etag":"","ItemInternalId":"71c6d470-f974-4965-aa92-b4cab774d32b","Link":"link","Empresa":"Pampa","TiCKER BBG":"PAMPAR 31","Ticker":"MGCMO","Name":"ON PAMPA ENERGIA CL 21","Vto":"48101","Cupon":"0.0795","Fq":"S","Vt":"1.00435616438356","Vr":"1","Px":"1.05828465547192","TIR":"0.0663871717453003","Duration":"3.8919658737681","Mduration":"3.64967431800434","Paridad":"1.05369458863376","Calificación":"AAA ","Monto Emitido":"410000000","Ley":"NY","Segmento":"O&G","CALL":"Yes","Paga":"CABLE","Amortización":"Bullet","volumen total":"20000"},{"@odata.etag":"","ItemInternalId":"7f6fdcf3-0d83-4944-9bfb-6d2e1511b191","Link":"link","Empresa":"YPF","TiCKER BBG":"YPFDAR 31","Ticker":"YMCXO","Name":"ON YPF CLASE 31","Vto":"48102","Cupon":"0.0875","Fq":"S","Vt":"1.00455479452055","Vr":"1","Px":"1.05120079194852","TIR":"0.0771931505203247","Duration":"4.1028220942169","Mduration":"3.80880819028146","Paridad":"1.04643449783169","Calificación":"B2","Monto Emitido":"500000000","Ley":"NY","Segmento":"O&G","CALL":"Yes","Paga":"CABLE","Amortización":"3 cuotas","volumen total":"746732"},{"@odata.etag":"","ItemInternalId":"d6e779de-aac5-4149-996d-a8ec15c4f5e1","Link":"link","Empresa":"PAE","TiCKER BBG":"PANAME 32","Ticker":"PNXCO","Name":"ON.PAN AMERCIAN ENERGY C31","Vto":"48334","Cupon":"0.085","Fq":"S","Vt":"1","Vr":"1.03516438356164","Px":"1.09178023428477","TIR":"0.0726901578903198","Duration":"4.16893500766202","Mduration":"3.88642981106599","Paridad":"1.05469261850792","Calificación":"AAA ","Monto Emitido":"400000000","Ley":"NY","Segmento":"O&G","CALL":"0","Paga":"CABLE","Amortización":"3 Cuotas","volumen total":"570000"},{"@odata.etag":"","ItemInternalId":"450ca57d-2c8a-4416-8258-1c218b59ce74","Link":"link","Empresa":"Pluspetrol","TiCKER BBG":"PLUSPETROL 32","Ticker":"PLC4O","Name":"ON PLUSPETROL C4","Vto":"48364","Cupon":"0.085","Fq":"S","Vt":"1.02794520547945","Vr":"1","Px":"1.071","TIR":"0.0775028562545776","Duration":"4.89704652457935","Mduration":"4.54481071317211","Paridad":"1.04188432835821","Calificación":"BB","Monto Emitido":"650000000","Ley":"NY","Segmento":"O&G","CALL":"yes","Paga":"CABLE","Amortización":"Bullet","volumen total":"386000"},{"@odata.etag":"","ItemInternalId":"78d053df-8c5a-4ed5-baf3-e7bf05add9fd","Link":"link","Empresa":"YPF LUZ","TiCKER BBG":"YPFLUZ32","Ticker":"YFCJO","Name":"ON YPF ENERGIA ELECTRICA C18","Vto":"48503","Cupon":"0.07875","Fq":"S","Vt":"1.03559931506849","Vr":"1","Px":"1.05977662999421","TIR":"0.0734050989151001","Duration":"4.462574770318","Mduration":"4.15740038390759","Paridad":"1.02334620598326","Calificación":"B2","Monto Emitido":"420000000","Ley":"NY","Segmento":"O&G","CALL":"Yes","Paga":"CABLE","Amortización":"3 cuotas","volumen total":"89000"},{"@odata.etag":"","ItemInternalId":"a93873b6-858d-4242-85ac-f01d7e61fe09","Link":"link","Empresa":"Tecpetrol","TiCKER BBG":"TECPETROL 33","Ticker":"TTCAO","Name":"ON.TECPETROL CLASE X","Vto":"48601","Cupon":"0.07625","Fq":"S","Vt":"1","Vr":"1.01399657534247","Px":"1.04105593136446","TIR":"0.0720342969894409","Duration":"5.15028310354445","Mduration":"4.80421486328172","Paridad":"1.02668584557384","Calificación":"AAA","Monto Emitido":"400000000","Ley":"NY","Segmento":"O&G","CALL":"-","Paga":"CABLE","Amortización":"3 cuotas (33,33y34)","volumen total":"54000"},{"@odata.etag":"","ItemInternalId":"a599a140-409e-422b-9bcb-536f31c227a9","Link":"link","Empresa":"Telecom","TiCKER BBG":"TECOAR 33","Ticker":"TLCPO","Name":"ON TELECOM ARGENTINA C24","Vto":"48727","Cupon":"0.0925","Fq":"S","Vt":"1","Vr":"1.03091780821918","Px":"1.06947446438911","TIR":"0.0865072965621948","Duration":"5.06875041824765","Mduration":"4.66517844315047","Paridad":"1.03740032024138","Calificación":"B/RR3","Monto Emitido":"800000000","Ley":"NY","Segmento":"Utilities","CALL":"no","Paga":"CABLE","Amortización":"2 cuotas","volumen total":"1393338"},{"@odata.etag":"","ItemInternalId":"d13dd30b-e5fa-499a-971b-28a268f8f738","Link":"link","Empresa":"Vista","TiCKER BBG":"VISTAA 33","Ticker":"VSCVO","Name":"ON VISTA OIL & GAS CL 29","Vto":"48740","Cupon":"0.085","Fq":"S","Vt":"1","Vr":"1.02561643835616","Px":"1.08297005211349","TIR":"0.0746039438247681","Duration":"4.86528470657073","Mduration":"4.52751428517379","Paridad":"1.05592111398804","Calificación":"AAA ","Monto Emitido":"500000000","Ley":"NY","Segmento":"O&G","CALL":"0","Paga":"CABLE","Amortización":"3 cuotas","volumen total":"887000"},{"@odata.etag":"","ItemInternalId":"4906fe30-4a03-47f5-8b93-68e726fea215","Link":"link","Empresa":"YPF","TiCKER BBG":"YPFDAR 34","Ticker":"YM34O","Name":"ON YPF CLASE 34","Vto":"48961","Cupon":"0.0825","Fq":"S","Vt":"1.01627397260274","Vr":"1","Px":"1.04099131441807","TIR":"0.079488205909729","Duration":"5.66565936463225","Mduration":"5.24846805515357","Paridad":"1.02432153383996","Calificación":"B2","Monto Emitido":"1100000000","Ley":"NY","Segmento":"O&G","CALL":"Yes","Paga":"CABLE","Amortización":"3 cuotas","volumen total":"2593949"},{"@odata.etag":"","ItemInternalId":"1a40d2a0-284b-4b86-8b41-4a8844dc7429","Link":"link","Empresa":"Pampa","TiCKER BBG":"PAMPAR 34","Ticker":"MGCOO","Name":"ON PAMPA ENERGIA CL 23","Vto":"49294","Cupon":"0.07875","Fq":"S","Vt":"1","Vr":"1.02243835616438","Px":"1.06052261725536","TIR":"0.0740303659439087","Duration":"6.46502129708617","Mduration":"6.01940271158386","Paridad":"1.03724846672795","Calificación":"AAA ","Monto Emitido":"700000000","Ley":"NY","Segmento":"O&G","CALL":"Yes","Paga":"CABLE","Amortización":"Bullet","volumen total":"387000"},{"@odata.etag":"","ItemInternalId":"b4e4d586-770f-4c58-a6e7-32d53bab17c4","Link":"link","Empresa":"Vista","TiCKER BBG":"VISTAA 35","Ticker":"VSCTO","Name":"ON VISTA OIL & GAS CL 27","Vto":"49653","Cupon":"0.07625","Fq":"S","Vt":"1","Vr":"1.02297945205479","Px":"1.04347137436067","TIR":"0.07430504322052","Duration":"6.39682488208539","Mduration":"5.95438411320231","Paridad":"1.02003160695429","Calificación":"AAA ","Monto Emitido":"600000000","Ley":"NY","Segmento":"O&G","CALL":"0","Paga":"CABLE","Amortización":"3 cuotas","volumen total":"350000"},{"@odata.etag":"","ItemInternalId":"64caeb98-b089-4e3c-9409-89cbc044c6e1","Link":"link","Empresa":"Pampa","TiCKER BBG":"PAMPAR 37","Ticker":"MGCRO","Name":"ON PAMPA ENERGIA CL 26","Vto":"50358","Cupon":"0.0775","Fq":"S","Vt":"1.02887671232877","Vr":"1","Px":"1.03610848870874","TIR":"0.0779646348953247","Duration":"7.75932084295706","Mduration":"7.19812189730188","Paridad":"1.007028807527","Calificación":"B-","Monto Emitido":"450000000","Ley":"NY","Segmento":"O&G","CALL":"Yes","Paga":"CABLE","Amortización":"Bullet","volumen total":"0"}]}