{"fx":{"mep":1433.18259784812,"cable":1487.21682847896},"local":[{"@odata.etag":"","ItemInternalId":"665ba3a3-b7a2-40bd-8de1-74be959bfb1d","Link":"link","Empresa":"Banco Galicia","Ticker":"BYCUO","Name":"ON BANCO GALICIA CL 28","Vto":"46171","Cupon":"0.059","Fq":"S","Vt":"0","Vr":"0","Px":"1.0315","TIR":"#¡NUM!","Duration":"#¡NUM!","Mduration":"#¡NUM!","Paridad":"#¡DIV/0!","Calificación":"AAA","Monto Emitido":"31296051","Ley":"ARG","Segmento":"FINANCIALS","CALL":"Yes","Paga":"MEP","Amortización":"Bullet","Vol Total":"371800","ISIN":"AR0355396844"},{"@odata.etag":"","ItemInternalId":"2d65ca7b-a250-4f18-828f-7827508aa9c2","Link":"link","Empresa":"John Deere","Ticker":"HJCBO","Name":"ON JOHN DEERE CLASE XI","Vto":"46172","Cupon":"0.06","Fq":"T","Vt":"1","Vr":"1","Px":"1.04","TIR":"0.0395767736434937","Duration":"1.90714397929181","Mduration":"1.8345388504667","Paridad":"1.04","Calificación":"A","Monto Emitido":"23898369","Ley":"ARG","Segmento":"AGRO","CALL":"-","Paga":"MEP","Amortización":"Bullet","Vol Total":"51892","ISIN":"AR0790183906"},{"@odata.etag":"","ItemInternalId":"b47b7bf7-9962-4d0b-a62f-e3c6e28f7f2d","Link":"link","Empresa":"MercadoPago","Ticker":"SXC2O","Name":"ON MERCADO PAGO SERVICIOS DE PROCESAMIENTO CLASE 2","Vto":"46174","Cupon":"0.0498","Fq":"A","Vt":"1.0317901369863","Vr":"1","Px":"1.0335","TIR":"-0.0700499517470598","Duration":"0.0136986301369863","Mduration":"0.0147305010228467","Paridad":"1.00165718100261","Calificación":" AA+","Monto Emitido":"50854527","Ley":"ARG","Segmento":"Utilities","CALL":"n/a","Paga":"MEP","Amortización":"Bullet","Vol Total":"137229","ISIN":"AR0487329176"},{"@odata.etag":"","ItemInternalId":"a6b1ff7c-1f19-4d5e-b9a0-a63c5ac08dbc","Link":"link","Empresa":"Vista","Ticker":"VSCNO","Name":"ON VISTA OIL & GAS CL 22","Vto":"46178","Cupon":"0.05","Fq":"T","Vt":"1.02369863013699","Vr":"1","Px":"0.9857","TIR":"3.8687805557251","Duration":"0.0246575342465753","Mduration":"0.00506441684203266","Paridad":"0.962881038404924","Calificación":"AAA ","Monto Emitido":"14668984","Ley":"ARG","Segmento":"O&G","CALL":"0","Paga":"CABLE","Amortización":"0","Vol Total":"0","ISIN":"AR0064363101"},{"@odata.etag":"","ItemInternalId":"31d17d39-3234-467c-ac4c-3e4aa929d924","Link":"link","Empresa":"Aluar","Ticker":"LMS9O","Name":"ON ALUAR 9 USD CABLE ","Vto":"46186","Cupon":"0.06","Fq":"T","Vt":"1.01232876712329","Vr":"1","Px":"1.06911108693287","TIR":"-0.631300826817751","Duration":"0.05","Mduration":"0.135611912466332","Paridad":"1.05609078952773","Calificación":"AAA","Monto Emitido":"50000000","Ley":"ARG","Segmento":"Industrials","CALL":"101","Paga":"CABLE","Amortización":"Bullet","Vol Total":"9308","ISIN":"AR0226237573"},{"@odata.etag":"","ItemInternalId":"0fa1c2dd-6ec0-48a8-8555-0264f3514755","Link":"link","Empresa":"MSU ENERGY","Ticker":"MSSEO","Name":"ON MSU ENERGY SERIE 13","Vto":"46220","Cupon":"0.065","Fq":"A","Vt":"1.05591780821918","Vr":"1","Px":"1.05283165052769","TIR":"0.0857193517684937","Duration":"0.13972602739726","Mduration":"0.128694424732934","Paridad":"0.997077274701245","Calificación":"A+ ","Monto Emitido":"25000000","Ley":"ARG","Segmento":"Energia","CALL":"0","Paga":"MEP","Amortización":"Bullet","Vol Total":"245","ISIN":"ARMSUS5600F5"},{"@odata.etag":"","ItemInternalId":"5d3d93b5-5907-4209-8895-21b6077d3fd9","Link":"link","Empresa":"Cresud","Ticker":"CS45O","Name":"ON CRESUD CL 45","Vto":"46256","Cupon":"0.06","Fq":"S","Vt":"1.00575342465753","Vr":"1","Px":"1.00350327408793","TIR":"0.0693928670883179","Duration":"0.243835616438356","Mduration":"0.228013131509151","Paridad":"0.997762721444008","Calificación":"AAA","Monto Emitido":"10199068","Ley":"ARG","Segmento":"Real Estate","CALL":"0","Paga":"CABLE","Amortización":"Bullet","Vol Total":"0","ISIN":"AR0529152206"},{"@odata.etag":"","ItemInternalId":"e5a53c53-03f4-4a79-8dfa-78db1fc3d52a","Link":"link","Empresa":"YPF LUZ","Ticker":"YFCNO","Name":"ON EF YPF ENERGIA ELECTRICA CLASE 22","Vto":"46298","Cupon":"0.06","Fq":"s","Vt":"1.00887671232877","Vr":"1","Px":"1.0245","TIR":"0.0152554750442505","Duration":"0.358904109589041","Mduration":"0.353511129376966","Paridad":"1.01548582446231","Calificación":" AA+","Monto Emitido":"79946259","Ley":"ARG","Segmento":"Utilities","CALL":"n/a","Paga":"MEP","Amortización":"Bullet","Vol Total":"42925","ISIN":"AR0361875989"},{"@odata.etag":"","ItemInternalId":"d50ec17f-f085-473a-8dec-2c96a180c2dc","Link":"link","Empresa":"San Miguel","Ticker":"SNSBO","Name":"ON SAN MIGUEL SERIE 11","Vto":"46309","Cupon":"0.095","Fq":"T","Vt":"1.01119178082192","Vr":"1","Px":"0.72","TIR":"1.70339136123657","Duration":"0.3762865999274","Mduration":"0.139190575705354","Paridad":"0.712031103946245","Calificación":"BBB-","Monto Emitido":"18037687","Ley":"ARG","Segmento":"Consumer","CALL":"no","Paga":"MEP","Amortización":"Bullet","Vol Total":"192","ISIN":"AR0792131879"},{"@odata.etag":"","ItemInternalId":"0020827a-1f07-46ae-8323-6e60e2b373b4","Link":"link","Empresa":"John Deere","Ticker":"HJCFO","Name":"ON JOHN DEERE CLASE XIV","Vto":"46316","Cupon":"0.05","Fq":"S","Vt":"1.00493150684931","Vr":"1","Px":"1.012","TIR":"0.0323718690872192","Duration":"0.402739726027397","Mduration":"0.390111100550893","Paridad":"1.00703380588877","Calificación":"A","Monto Emitido":"28658217","Ley":"ARG","Segmento":"AGRO","CALL":"0","Paga":"MEP","Amortización":"Bullet","Vol Total":"11200","ISIN":"AR0594233345"},{"@odata.etag":"","ItemInternalId":"9d84962c-2e4c-4b18-86f3-63fa33c20699","Link":"link","Empresa":"Oiltanking","Ticker":"OTS5O","Name":"ON OILTANKING EBYTEM SA S5","Vto":"46318","Cupon":"0.0669","Fq":"S","Vt":"1.00623178082192","Vr":"1","Px":"1.01773493635078","TIR":"0.0384756803512573","Duration":"0.408219178082192","Mduration":"0.393094596056515","Paridad":"1.01143191434429","Calificación":"AAA","Monto Emitido":"50000000","Ley":"ARG","Segmento":"O&G","CALL":"n/a","Paga":"MEP","Amortización":"Bullet","Vol Total":"12986","ISIN":"AR0034370418"},{"@odata.etag":"","ItemInternalId":"9a1ee520-cb78-4046-b8c6-341812e5b7c6","Link":"link","Empresa":"Edenor","Ticker":"DNC3O","Name":"ON EDENOR CL 3","Vto":"46348","Cupon":"0.0975","Fq":"S","Vt":"1.00133561643836","Vr":"1","Px":"1.02","TIR":"0.0584692049026489","Duration":"0.495890410958904","Mduration":"0.468497721673927","Paridad":"1.01863948835459","Calificación":"A","Monto Emitido":"95762688","Ley":"ARG","Segmento":"Utilities","CALL":"0","Paga":"MEP","Amortización":"Bullet","Vol Total":"420927","ISIN":"AR0140482933"},{"@odata.etag":"","ItemInternalId":"dd10462b-1b12-4999-b6d5-ceb1d36cf900","Link":"link","Empresa":"YPF LUZ","Ticker":"YFCKO","Name":"ON EF YPF ENERGIA ELECTRICA CLASE 19","Vto":"46348","Cupon":"0.0525","Fq":"T","Vt":"1.00071917808219","Vr":"1","Px":"1.02","TIR":"0.0129094743728638","Duration":"0.492630612579492","Mduration":"0.486352063084908","Paridad":"1.01926696553848","Calificación":" AA+","Monto Emitido":"49018232","Ley":"ARG","Segmento":"Utilities","CALL":"n/a","Paga":"MEP","Amortización":"Bullet","Vol Total":"96816","ISIN":"AR0015491712"},{"@odata.etag":"","ItemInternalId":"87251d5c-8b03-465b-98a3-24fa257438ca","Link":"link","Empresa":"Banco Galicia","Ticker":"BYCWO","Name":"ON BANCO GALICIA CL XXX","Vto":"46356","Cupon":"0.06","Fq":"S","Vt":"1.00213698630137","Vr":"1","Px":"1.02708475682733","TIR":"0.0110365724563599","Duration":"0.512328767123288","Mduration":"0.506736137030693","Paridad":"1.0248945711684","Calificación":"AAA","Monto Emitido":"144323518","Ley":"ARG","Segmento":"FINANCIALS","CALL":"Yes","Paga":"MEP","Amortización":"Bullet","Vol Total":"0","ISIN":"AR0098652693"},{"@odata.etag":"","ItemInternalId":"f4d40fa7-947e-4812-b17b-0eae0a550adb","Link":"link","Empresa":"Sidersa","Ticker":"SIC1O","Name":"ON SIDERSA CLASE 1","Vto":"46365","Cupon":"0.065","Fq":"S","Vt":"1.03009589041096","Vr":"1","Px":"1.032","TIR":"0.0622153234481811","Duration":"0.521274108222656","Mduration":"0.49074241042813","Paridad":"0","Calificación":"A+","Monto Emitido":"39443215","Ley":"ARG","Segmento":"Industrials","CALL":"No","Paga":"MEP","Amortización":"Bullet","Vol Total":"10085","ISIN":"AR0997031304"},{"@odata.etag":"","ItemInternalId":"7aafe09c-b3de-42fb-9132-6a7a2975be6e","Link":"link","Empresa":"Banco Galicia","Ticker":"BYCXO","Name":"ON BANCO GALICIA CL XXXI","Vto":"46386","Cupon":"0.055","Fq":"S","Vt":"1.02350684931507","Vr":"1","Px":"1.063","TIR":"-0.0109766054153442","Duration":"0.581009473063534","Mduration":"0.587457765149763","Paridad":"1.03858611274693","Calificación":"AAA","Monto Emitido":"71863952","Ley":"ARG","Segmento":"FINANCIALS","CALL":"Yes","Paga":"MEP","Amortización":"Bullet","Vol Total":"0","ISIN":"AR0185542955"},{"@odata.etag":"","ItemInternalId":"fc1a9667-cded-493b-944e-723bd8a3bb7c","Link":"link","Empresa":"YPF","Ticker":"YM41O","Name":"ON YPF CL 41","Vto":"46395","Cupon":"0.06","Fq":"T","Vt":"1.00805479452055","Vr":"1","Px":"1.029","TIR":"0.0260226011276245","Duration":"0.608201616449157","Mduration":"0.592776041951442","Paridad":"1.02077784421373","Calificación":"AAA ","Monto Emitido":"99005943","Ley":"ARG","Segmento":"O&G","CALL":"0","Paga":"MEP","Amortización":"Bullet","Vol Total":"255658","ISIN":"AR0675705039"},{"@odata.etag":"","ItemInternalId":"10f5a554-4012-479e-846e-ad22973a3dbe","Link":"link","Empresa":"Cresud","Ticker":"CS44O","Name":"ON CRESUD CL 44","Vto":"46404","Cupon":"0.06","Fq":"S","Vt":"1.0213698630137","Vr":"1","Px":"1.029","TIR":"0.048070387840271","Duration":"0.632015677794975","Mduration":"0.603027893095379","Paridad":"1.00747049356223","Calificación":"AAA","Monto Emitido":"39765830","Ley":"ARG","Segmento":"Real Estate","CALL":"0","Paga":"MEP","Amortización":"Bullet","Vol Total":"24531","ISIN":"AR0941280056"},{"@odata.etag":"","ItemInternalId":"36d8749a-de7a-41c1-9523-46d0e973f128","Link":"link","Empresa":"Cresud","Ticker":"CS51O","Name":"ON CRESUD CL 51","Vto":"46407","Cupon":"0.0575","Fq":"S","Vt":"1.02000684931507","Vr":"1","Px":"1.0325","TIR":"0.0381907892227173","Duration":"0.6382101973726","Mduration":"0.61473305677314","Paridad":"1.01224810469981","Calificación":"AAA","Monto Emitido":"46778518","Ley":"ARG","Segmento":"Real Estate","CALL":"n/a","Paga":"MEP","Amortización":"Bullet","Vol Total":"94997","ISIN":"AR0452589218"},{"@odata.etag":"","ItemInternalId":"53a6cea1-c6eb-4bba-9ce1-9741f3d88ea1","Link":"link","Empresa":"Tarjeta Naranja","Ticker":"T672O","Name":"ON TARJETA NARANJA CL LXVII SERIE II","Vto":"46440","Cupon":"0.05","Fq":"T","Vt":"1.00068493150685","Vr":"1","Px":"0.998477097160265","TIR":"0.0540978002548218","Duration":"0.733220391765247","Mduration":"0.69559047707717","Paridad":"0.997793676833667","Calificación":"AAA(arg)","Monto Emitido":"115084281","Ley":"ARG","Segmento":"FINANCIALS","CALL":"-","Paga":"MEP","Amortización":"Bullet","Vol Total":"0","ISIN":""},{"@odata.etag":"","ItemInternalId":"8e80d0ee-ed6b-4c2b-9bbf-dbd0c29e7f39","Link":"link","Empresa":"EDESA","Ticker":"DEC2O","Name":"ON EDESA CLASE 2","Vto":"46442","Cupon":"0.085","Fq":"S","Vt":"1","Vr":"1.02142465753425","Px":"1.009","TIR":"0.104916157722473","Duration":"0.727392301396427","Mduration":"0.658323526461751","Paridad":"1.009","Calificación":"A-","Monto Emitido":"22492616","Ley":"ARG","Segmento":"Utilities","CALL":"0","Paga":"MEP","Amortización":"Bullet","Vol Total":"88585","ISIN":"AR0021181018"},{"@odata.etag":"","ItemInternalId":"ad1072e6-8906-495c-b576-bda412dd66c3","Link":"link","Empresa":"YPF LUZ","Ticker":"YFCGO","Name":"ON YPF ENERGIA ELECTRICA CL 15","Vto":"46445","Cupon":"0.06","Fq":"T","Vt":"1","Vr":"1","Px":"1.04","TIR":"0.00688547611236572","Duration":"0.750514355582974","Mduration":"0.745382045315369","Paridad":"1.04","Calificación":" AA+","Monto Emitido":"11287656","Ley":"ARG","Segmento":"Utilities","CALL":"0","Paga":"MEP","Amortización":"Bullet","Vol Total":"6272","ISIN":"AR0704160875"},{"@odata.etag":"","ItemInternalId":"b44998e9-1971-4ded-9ade-8c365705c509","Link":"link","Empresa":"Irsa","Ticker":"IRCJO","Name":"ON IRSA CL 18","Vto":"46446","Cupon":"0.07","Fq":"S","Vt":"1.01687671232877","Vr":"1","Px":"1.0335","TIR":"0.0476887845993042","Duration":"0.744821083129448","Mduration":"0.710918255571773","Paridad":"1.01634739734885","Calificación":"AA+","Monto Emitido":"21408926","Ley":"ARG","Segmento":"Real Estate","CALL":"0","Paga":"MEP","Amortización":"Bullet","Vol Total":"34437","ISIN":"AR0961375257"},{"@odata.etag":"","ItemInternalId":"00fc8b81-30fa-4974-afac-54a3ddb05a15","Link":"link","Empresa":"Vista","Ticker":"VSCOO","Name":"ON VISTA OIL & GAS CL 23","Vto":"46452","Cupon":"0.065","Fq":"S","Vt":"1.01460273972603","Vr":"1","Px":"1.04275312806006","TIR":"0.0279654932022095","Duration":"0.765274613766128","Mduration":"0.744455547220972","Paridad":"1.02774523193347","Calificación":"AAA ","Monto Emitido":"92202616","Ley":"ARG","Segmento":"O&G","CALL":"0","Paga":"CABLE","Amortización":"Bullet","Vol Total":"7633","ISIN":"AR0399155156"},{"@odata.etag":"","ItemInternalId":"01aa1f7a-7e1d-4399-b556-a1c719f5c7e0","Link":"link","Empresa":"Genneia","Ticker":"GN43O","Name":"ON GENNEIA S.A. CL 43","Vto":"46454","Cupon":"0.0625","Fq":"T","Vt":"1.01369863013699","Vr":"1","Px":"1.03964421716897","TIR":"0.0302002477645874","Duration":"0.76866600041354","Mduration":"0.74613261070501","Paridad":"1.02559497099101","Calificación":"A+","Monto Emitido":"20697951","Ley":"ARG","Segmento":"Utilities","CALL":"0","Paga":"MEP","Amortización":"Bullet","Vol Total":"0","ISIN":"AR0667572231"},{"@odata.etag":"","ItemInternalId":"fce1c7a1-05e8-4e6b-921a-84a50f38ae40","Link":"link","Empresa":"CGC","Ticker":"CP37O","Name":"ON CGC CIA GENERAL COMBUST CL 37","Vto":"46456","Cupon":"0.07","Fq":"t","Vt":"1.01495890410959","Vr":"1","Px":"1.01","TIR":"0.0787554121017456","Duration":"0.760709362237889","Mduration":"0.705173159461415","Paridad":"0.995114182367867","Calificación":"AA- ","Monto Emitido":"27630742","Ley":"ARG","Segmento":"O&G","CALL":"0","Paga":"MEP","Amortización":"Bullet","Vol Total":"0","ISIN":"AR0172788611"},{"@odata.etag":"","ItemInternalId":"fe4e9690-4730-489c-847e-283deb161304","Link":"link","Empresa":"Aluar","Ticker":"LMS8O","Name":"ON ALUAR 8 USD CABLE ","Vto":"46467","Cupon":"0.0625","Fq":"T","Vt":"1.01147260273973","Vr":"1","Px":"1.035","TIR":"0.0104768800735474","Duration":"0.445660713008532","Mduration":"0.441039989926434","Paridad":"1.02326053834434","Calificación":"AAA","Monto Emitido":"100000000","Ley":"ARG","Segmento":"Industrials","CALL":"0","Paga":"CABLE","Amortización":"1","Vol Total":"27423","ISIN":"AR0787528089"},{"@odata.etag":"","ItemInternalId":"f568ba9e-3b6a-4172-b1d8-1960b16f1b34","Link":"link","Empresa":"Vista","Ticker":"VSCWO","Name":"ON VISTA OIL & GAS CL 30","Vto":"46492","Cupon":"0.06","Fq":"T","Vt":"1.00690410958904","Vr":"1","Px":"1.03","TIR":"0.0338071870803833","Duration":"0.863305465043381","Mduration":"0.835073963338828","Paridad":"1.0229375272094","Calificación":"AAA ","Monto Emitido":"73256123","Ley":"ARG","Segmento":"O&G","CALL":"N/A","Paga":"MEP","Amortización":"Bullet","Vol Total":"104075","ISIN":"AR0652555118"},{"@odata.etag":"","ItemInternalId":"2c3f3f8a-061f-4058-8385-695c2c732799","Link":"link","Empresa":"Pan american","Ticker":"PN42O","Name":"ON PAN AMERICAN ENERGY CL 42","Vto":"46494","Cupon":"0.06","Fq":"S","Vt":"1.00657534246575","Vr":"1","Px":"1.037","TIR":"0.0251937532424927","Duration":"0.881567988873123","Mduration":"0.859903785099052","Paridad":"1.03022591181274","Calificación":"AAA ","Monto Emitido":"56135832","Ley":"ARG","Segmento":"O&G","CALL":"0","Paga":"MEP","Amortización":"Bullet","Vol Total":"29780","ISIN":"AR0081130814"},{"@odata.etag":"","ItemInternalId":"e93b12a3-810f-4bc2-b12e-9f0d3f7bfbb8","Link":"link","Empresa":"Oiltanking","Ticker":"OTS2O","Name":"ON OILTANKING EBYTEM SA S2","Vto":"46501","Cupon":"0.07","Fq":"T","Vt":"1.00632876712329","Vr":"1","Px":"1.025","TIR":"0.0494570589065552","Duration":"0.889723919627084","Mduration":"0.8477944972366","Paridad":"1.01855381013313","Calificación":"AAA","Monto Emitido":"32947113","Ley":"ARG","Segmento":"O&G","CALL":"0","Paga":"MEP","Amortización":"Bullet","Vol Total":"49569","ISIN":"AR0182698750"},{"@odata.etag":"","ItemInternalId":"53346507-31cd-45e1-8b98-765a1c87f0ce","Link":"link","Empresa":"YPF","Ticker":"YM37O","Name":"ON YPF CL 37","Vto":"46514","Cupon":"0.07","Fq":"T","Vt":"1.00383561643836","Vr":"1","Px":"1.03336448699815","TIR":"0.0385668039321899","Duration":"0.920383062405075","Mduration":"0.886204969117392","Paridad":"1.02941604190591","Calificación":"AAA ","Monto Emitido":"139501701","Ley":"ARG","Segmento":"O&G","CALL":"0","Paga":"MEP","Amortización":"Bullet","Vol Total":"112606","ISIN":"AR0657794191"},{"@odata.etag":"","ItemInternalId":"1decad80-a70e-4229-9646-59afff20b715","Link":"link","Empresa":"BBVA","Ticker":"BF45O","Name":"ON BBVA CL 45","Vto":"46515","Cupon":"0.0325","Fq":"S","Vt":"1.00169178082192","Vr":"1","Px":"0.99","TIR":"0.0454628974199295","Duration":"0.945337978745243","Mduration":"0.904229103757022","Paridad":"0.98832796570186","Calificación":"Bullet","Monto Emitido":"25072002","Ley":"ARG","Segmento":"FINANCIALS","CALL":"A1+","Paga":"MEP","Amortización":"0","Vol Total":"0","ISIN":"AR0463317443"},{"@odata.etag":"","ItemInternalId":"88909c2c-5024-4def-900e-dda8b856d823","Link":"link","Empresa":"Arcor","Ticker":"RCCRO","Name":"ON ARCOR CL 26","Vto":"46516","Cupon":"0.0675","Fq":"S","Vt":"1.00332876712329","Vr":"1","Px":"1.037","TIR":"0.031406044960022","Duration":"0.93729144870031","Mduration":"0.908751168640514","Paridad":"1.03355952104638","Calificación":"AAA ","Monto Emitido":"68415046","Ley":"ARG","Segmento":"Consumer","CALL":"0","Paga":"MEP","Amortización":"Bullet","Vol Total":"9299","ISIN":"AR0016944933"},{"@odata.etag":"","ItemInternalId":"75f5d51c-e52d-4f5d-a38c-882d2bcfe0ba","Link":"link","Empresa":"YPF LUZ","Ticker":"YFCMO","Name":"ON EF YPF ENERGIA ELECTRICA CLASE 21","Vto":"46527","Cupon":"0.065","Fq":"T","Vt":"1.00124657534247","Vr":"1","Px":"1.0255","TIR":"0.0402499914169312","Duration":"0.957511588928474","Mduration":"0.920462962584831","Paridad":"1.02422322857807","Calificación":" AA+","Monto Emitido":"53827026","Ley":"ARG","Segmento":"Utilities","CALL":"0","Paga":"MEP","Amortización":"Bullet","Vol Total":"7523","ISIN":"AR0975634988"},{"@odata.etag":"","ItemInternalId":"34dda17f-3527-4f3e-b93a-36fb60f344ab","Link":"link","Empresa":"ICBC Argentina","Ticker":"ICC6O","Name":"ON ICBC ARGENTINA CL VI","Vto":"46529","Cupon":"0.037","Fq":"T","Vt":"1.00050684931507","Vr":"1","Px":"0","TIR":"#¡NUM!","Duration":"#¡NUM!","Mduration":"#¡NUM!","Paridad":"0","Calificación":"A1(arg)","Monto Emitido":"45080301","Ley":"ARG","Segmento":"FINANCIALS","CALL":"n/a","Paga":"MEP","Amortización":"Bullet","Vol Total":"#N/D","ISIN":""},{"@odata.etag":"","ItemInternalId":"f3cccaac-e9c3-40a8-bd25-2fd53075a02d","Link":"link","Empresa":"Telecom","Ticker":"TLCQO","Name":"ON.TELECOM ARGENTINA C.  25","Vto":"46570","Cupon":"0.075","Fq":"T","Vt":"1.01150684931507","Vr":"1","Px":"1.05031975845936","TIR":"0.0391919851303101","Duration":"1.05213881667057","Mduration":"1.01245855599881","Paridad":"1.03837137550831","Calificación":"AA+","Monto Emitido":"50489739","Ley":"ARG","Segmento":"Utilities","CALL":"1","Paga":"MEP","Amortización":"Bullet","Vol Total":"66975","ISIN":"AR0006792755"},{"@odata.etag":"","ItemInternalId":"0f9d0419-2fbc-4512-baef-cd918d347044","Link":"link","Empresa":"Profertil","Ticker":"PFC2O","Name":"ON PROFERTIL S.A. CLASE 2","Vto":"46582","Cupon":"0.0725","Fq":"S","Vt":"1.02641780821918","Vr":"1","Px":"1.06","TIR":"0.0421763563156128","Duration":"1.08111879137188","Mduration":"1.0373664541709","Paridad":"1.032717857691","Calificación":"AAA ","Monto Emitido":"54325110","Ley":"ARG","Segmento":"AGRO","CALL":"0","Paga":"MEP","Amortización":"Bullet","Vol Total":"24692","ISIN":"AR0416362439"},{"@odata.etag":"","ItemInternalId":"c83d6396-443d-43dd-af21-c497fd2775c7","Link":"link","Empresa":"YPF","Ticker":"YM38O","Name":"ON YPF CL 38","Vto":"46590","Cupon":"0.075","Fq":"T","Vt":"1.00719178082192","Vr":"1","Px":"1.05","TIR":"0.0374154901504517","Duration":"1.10948710582568","Mduration":"1.06947227640179","Paridad":"1.04250255015301","Calificación":"AAA ","Monto Emitido":"250000000","Ley":"ARG","Segmento":"O&G","CALL":"0","Paga":"MEP","Amortización":"Bullet","Vol Total":"184700","ISIN":"AR0419238511"},{"@odata.etag":"","ItemInternalId":"90721f76-9d2c-456b-a135-4e231fc6336e","Link":"link","Empresa":"MSU SA","Ticker":"MSSFO","Name":"ON MSU SERIE 14","Vto":"46591","Cupon":"0.075","Fq":"S","Vt":"1.02547945205479","Vr":"1","Px":"1.02568926123382","TIR":"0.076054539680481","Duration":"1.1031006281058","Mduration":"1.02513449590887","Paridad":"1.00020459618045","Calificación":"A+","Monto Emitido":"33500000","Ley":"ARG","Segmento":"AGRO","CALL":"no","Paga":"MEP","Amortización":"Bullet","Vol Total":"176759","ISIN":"AR0820572623"},{"@odata.etag":"","ItemInternalId":"0ec1e5e4-2a9a-4232-abd3-815c92150c8c","Link":"link","Empresa":"Loma Negra","Ticker":"LOC5O","Name":"ON LOMA NEGRA S.A CL 5","Vto":"46592","Cupon":"0.08","Fq":"S","Vt":"1.02695890410959","Vr":"1","Px":"1.06406539005549","TIR":"0.0469671583175659","Duration":"1.10883931022562","Mduration":"1.0590965546689","Paridad":"1.03613239614303","Calificación":"AAA","Monto Emitido":"112878134","Ley":"ARG","Segmento":"Industrials","CALL":"0","Paga":"MEP","Amortización":"Bullet","Vol Total":"66350","ISIN":"AR0579536985"},{"@odata.etag":"","ItemInternalId":"8b889fa8-406b-4ce3-b055-66a283531f9d","Link":"link","Empresa":"Pan american","Ticker":"PN38O","Name":"ON PAN AMERICAN ENERGY CL 38","Vto":"46610","Cupon":"0.065","Fq":"S","Vt":"1.01869863013699","Vr":"1","Px":"1.04686155285313","TIR":"0.0412240266799927","Duration":"1.1626058134008","Mduration":"1.11657605242538","Paridad":"1.02764598074738","Calificación":"AAA ","Monto Emitido":"120000000","Ley":"ARG","Segmento":"O&G","CALL":"0","Paga":"CABLE","Amortización":"Bullet","Vol Total":"140550","ISIN":"AR0554009248"},{"@odata.etag":"","ItemInternalId":"63d226f2-293f-468e-a84e-0443360a6605","Link":"link","Empresa":"Scania","Ticker":"SBC1O","Name":"ON SCANIA CREDIT ARG CLASE 1","Vto":"46635","Cupon":"0.0875","Fq":"T","Vt":"0.877111643835616","Vr":"0.86","Px":"0.8899","TIR":"0.0654715394973755","Duration":"0.640463855703955","Mduration":"0.601108365603165","Paridad":"1.01458007798011","Calificación":"A+","Monto Emitido":"40000000","Ley":"ARG","Segmento":"Utilities","CALL":"0","Paga":"MEP","Amortización":"7 cuotas","Vol Total":"25072","ISIN":"AR0200205687"},{"@odata.etag":"","ItemInternalId":"e9693468-de9c-4cd1-a54c-a06617461eac","Link":"link","Empresa":"Pan american","Ticker":"PN34O","Name":"ON PAN AMERICAN ENERGY CL 34","Vto":"46657","Cupon":"0.0497","Fq":"S","Vt":"1.00830602739726","Vr":"1","Px":"1.023","TIR":"0.0386395788192749","Duration":"1.30123798375688","Mduration":"1.25282919146614","Paridad":"1.01457292945146","Calificación":"AAA ","Monto Emitido":"23055471","Ley":"ARG","Segmento":"O&G","CALL":"0","Paga":"MEP","Amortización":"Bullet","Vol Total":"27557","ISIN":"AR0770773957"},{"@odata.etag":"","ItemInternalId":"a0055571-7034-4213-bf6b-a6370322b042","Link":"link","Empresa":"CGC","Ticker":"CP36O","Name":"ON CGC CIA GENERAL COMBUST CL 36","Vto":"46670","Cupon":"0.065","Fq":"S","Vt":"1.0083698630137","Vr":"1","Px":"0.9899","TIR":"0.0805947637557984","Duration":"1.3308685932907","Mduration":"1.23160747944496","Paridad":"0.981683444050482","Calificación":"AA- ","Monto Emitido":"68262474","Ley":"ARG","Segmento":"O&G","CALL":"0","Paga":"MEP","Amortización":"Bullet","Vol Total":"11083","ISIN":"AR0015464982"},{"@odata.etag":"","ItemInternalId":"99c51371-9c8b-424d-aa71-0a63a84af5b1","Link":"link","Empresa":"Tecpetrol","Ticker":"TTCBO","Name":"ON TECPETROL CLASE 11","Vto":"46676","Cupon":"0.065","Fq":"S","Vt":"1.00730136986301","Vr":"1","Px":"1.0475","TIR":"0.0352297449111938","Duration":"1.3484494638201","Mduration":"1.30256058662203","Paridad":"1.03990725252608","Calificación":"AAA","Monto Emitido":"114452024","Ley":"ARG","Segmento":"O&G","CALL":"-","Paga":"MEP","Amortización":"Bullet","Vol Total":"20530","ISIN":"AR0152326457"},{"@odata.etag":"","ItemInternalId":"a49bc686-545f-4962-9bd7-a56977277237","Link":"link","Empresa":"Irsa","Ticker":"IRCNO","Name":"ON IRSA CL 22","Vto":"46683","Cupon":"0.0575","Fq":"S","Vt":"1.01953424657534","Vr":"1","Px":"1.035","TIR":"0.0463848352432251","Duration":"1.35224192935038","Mduration":"1.29229885966004","Paridad":"1.01516943003789","Calificación":"AA+","Monto Emitido":"15799810","Ley":"ARG","Segmento":"Real Estate","CALL":"0","Paga":"MEP","Amortización":"Bullet","Vol Total":"4652","ISIN":"AR0275431465"},{"@odata.etag":"","ItemInternalId":"a5edb0e0-dcc7-4fac-a55c-9ee00d398602","Link":"link","Empresa":"Minera Exar","Ticker":"XMC1O","Name":"ON MINERA EXAR CLASE 1","Vto":"46702","Cupon":"0.08","Fq":"S","Vt":"1","Vr":"1","Px":"1.02","TIR":"0.0731326246261597","Duration":"2.52178124418214","Mduration":"2.34992505708289","Paridad":"1.02","Calificación":"AA","Monto Emitido":"50000000","Ley":"ARG","Segmento":"Mineria","CALL":"0","Paga":"MEP","Amortización":"2 cuotas ","Vol Total":"120035","ISIN":"AR0778941762"},{"@odata.etag":"","ItemInternalId":"27500bbe-dbbd-4833-8baa-a6836b2214e3","Link":"link","Empresa":"Tarjeta Naranja","Ticker":"T673O","Name":"ON TARJETA NARANJA CL LXVII SERIE III","Vto":"46713","Cupon":"0.04","Fq":"todo a vto","Vt":"1.00054794520548","Vr":"1","Px":"0","TIR":"#¡NUM!","Duration":"#¡NUM!","Mduration":"#¡NUM!","Paridad":"0","Calificación":"AAA(arg)","Monto Emitido":"13849604","Ley":"ARG","Segmento":"FINANCIALS","CALL":"-","Paga":"CABLE","Amortización":"Bullet","Vol Total":"0","ISIN":""},{"@odata.etag":"","ItemInternalId":"06f46707-0141-4d84-a4c8-197900315a57","Link":"link","Empresa":"John Deere","Ticker":"HJCHO","Name":"ON JOHN DEERE CLASE 16","Vto":"46769","Cupon":"0.07","Fq":"S","Vt":"1.02493150684931","Vr":"1","Px":"1.045","TIR":"0.0607145547866821","Duration":"1.9816136929632","Mduration":"1.86818751946109","Paridad":"1.01958032611601","Calificación":"A","Monto Emitido":"50000000","Ley":"ARG","Segmento":"AGRO","CALL":"0","Paga":"MEP","Amortización":"Bullet","Vol Total":"1200","ISIN":"AR0262204990"},{"@odata.etag":"","ItemInternalId":"30ef841d-d2dc-45c4-81d3-168036442dbb","Link":"link","Empresa":"Genneia","Ticker":"GN48O","Name":"ON GENNEIA S.A. CL 48","Vto":"46817","Cupon":"0.065","Fq":"S","Vt":"1.01478082191781","Vr":"1","Px":"1.031","TIR":"0.0558851099014282","Duration":"1.68633999907653","Mduration":"1.59708663685385","Paridad":"1.01598293713468","Calificación":"AA+","Monto Emitido":"27760264","Ley":"ARG","Segmento":"Utilities","CALL":"YES ","Paga":"MEP","Amortización":"Bullet","Vol Total":"37948","ISIN":"AR0580434501"},{"@odata.etag":"","ItemInternalId":"69d07a11-9ba5-483b-a8e9-a070cbb0fd39","Link":"link","Empresa":"CGC","Ticker":"CP40O","Name":"ON CGC CIA GENERAL COMBUST CL 40","Vto":"46821","Cupon":"0.095","Fq":"t","Vt":"1.02056164383562","Vr":"1","Px":"1.033","TIR":"0.09028892993927","Duration":"1.63210762538605","Mduration":"1.49694964386821","Paridad":"1.01218775586905","Calificación":"AA- ","Monto Emitido":"55197497","Ley":"ARG","Segmento":"O&G","CALL":"n/a","Paga":"MEP","Amortización":"Bullet","Vol Total":"29824","ISIN":"AR0360181769"},{"@odata.etag":"","ItemInternalId":"bcfacb3c-3aa1-4964-8589-25660bf26f4d","Link":"link","Empresa":"Pluspetrol","Ticker":"PLC3O","Name":"ON PLUSPETROL C3 USD 7,25%","Vto":"46873","Cupon":"0.0725","Fq":"S","Vt":"1.0232397260274","Vr":"1","Px":"1.06","TIR":"0.0527466630935669","Duration":"1.80133836479863","Mduration":"1.71108437380868","Paridad":"1.03592537802976","Calificación":"A+","Monto Emitido":"90722914","Ley":"ARG","Segmento":"O&G","CALL":"0","Paga":"MEP","Amortización":"Bullet","Vol Total":"35524","ISIN":"AR0808016403"},{"@odata.etag":"","ItemInternalId":"b05b0aa7-2f90-4135-a357-879efb09a091","Link":"link","Empresa":"Cresud","Ticker":"CS52O","Name":"ON CRESUD CL 52","Vto":"46873","Cupon":"0.0475","Fq":"S","Vt":"1.00351369863014","Vr":"1","Px":"0.9995","TIR":"0.0500718545913696","Duration":"1.86855604450499","Mduration":"1.77945541187001","Paridad":"0.996000354917311","Calificación":"AAA","Monto Emitido":"41201813","Ley":"ARG","Segmento":"Real Estate","CALL":"n/a","Paga":"MEP","Amortización":"Bullet","Vol Total":"121100","ISIN":"AR0122431304"},{"@odata.etag":"","ItemInternalId":"f83fc0f7-b9d0-47a2-b973-74f0217d27f1","Link":"link","Empresa":"BBVA","Ticker":"BF44O","Name":"ON BBVA CL 44","Vto":"46881","Cupon":"0.05","Fq":"S","Vt":"1.00260273972603","Vr":"1","Px":"1.0025","TIR":"0.0506599092483521","Duration":"1.87871168867246","Mduration":"1.78812541730701","Paridad":"0.999897526984561","Calificación":"Bullet","Monto Emitido":"48018887","Ley":"ARG","Segmento":"FINANCIALS","CALL":"AAA","Paga":"MEP","Amortización":"Bullet","Vol Total":"0","ISIN":"AR0576992660"},{"@odata.etag":"","ItemInternalId":"0eb51677-fa22-4952-a71f-df7ecdaabe03","Link":"link","Empresa":"Celulosa","Ticker":"CRCJO","Name":"ON CELULOSA CLASE 18","Vto":"46889","Cupon":"0.0925","Fq":"t","Vt":"0.501393835616438","Vr":"0.5","Px":"0.209324339027309","TIR":"1.91963891983032","Duration":"0.752020187741663","Mduration":"0.257573011043902","Paridad":"0.417484867499329","Calificación":"D","Monto Emitido":"34873114","Ley":"ARG","Segmento":"Utilities","CALL":"n/a","Paga":"MEP","Amortización":"16 cuotas","Vol Total":"#N/D","ISIN":"AR0904133144"},{"@odata.etag":"","ItemInternalId":"75a36911-cd8c-4340-8ef2-fb3d23e7b153","Link":"link","Empresa":"Oleoductos del valle","Ticker":"OLC2O","Name":"ON OLEDUCTOS DEL VALLE CLASE 2","Vto":"46913","Cupon":"0.01","Fq":"T","Vt":"1.0146301369863","Vr":"1","Px":"0.855335584482102","TIR":"0.0926681184768677","Duration":"2.01332453415554","Mduration":"1.84257644211495","Paridad":"0.843002344699377","Calificación":"AAA ","Monto Emitido":"43324070","Ley":"ARG","Segmento":"O&G","CALL":"0","Paga":"MEP","Amortización":"Bullet","Vol Total":"0","ISIN":"AROLDV560021"},{"@odata.etag":"","ItemInternalId":"62b75076-3cb0-4a34-9b10-44bff25c6283","Link":"link","Empresa":"Oleoductos del valle","Ticker":"OLC5O","Name":"ON OLEDUCTOS DEL VALLE CLASE 5","Vto":"46916","Cupon":"0.0789","Fq":"s","Vt":"1.03588328767123","Vr":"1","Px":"1.082","TIR":"0.0547257384397482","Duration":"1.86980823389869","Mduration":"1.77279094057635","Paridad":"1.04451921647702","Calificación":"AAA ","Monto Emitido":"85000000","Ley":"ARG","Segmento":"O&G","CALL":"0","Paga":"MEP","Amortización":"Bullet","Vol Total":"28003","ISIN":"AR0467419146"},{"@odata.etag":"","ItemInternalId":"fcecda07-bf71-4a1d-a4e4-11dc8089b778","Link":"link","Empresa":"Havanna","Ticker":"HVS1O","Name":"ON HAVANNA SERIE 1","Vto":"46942","Cupon":"0.0875","Fq":"T","Vt":"1.01174657534247","Vr":"1","Px":"1.03859759547383","TIR":"0.0755291318893433","Duration":"1.94205264591781","Mduration":"1.80567182081463","Paridad":"1.02653927454341","Calificación":"A","Monto Emitido":"18534790","Ley":"ARG","Segmento":"consumer","CALL":"-","Paga":"MEP","Amortización":"Bullet","Vol Total":"6239","ISIN":"AR0105218975"},{"@odata.etag":"","ItemInternalId":"d4161333-96ff-4751-919c-a729c2abc808","Link":"link","Empresa":"Edenor","Ticker":"DNC5O","Name":"ON EDENOR CL 5","Vto":"46970","Cupon":"0.095","Fq":"S","Vt":"1.0288904109589","Vr":"1","Px":"1.082","TIR":"0.0623811864852905","Duration":"1.56830073378615","Mduration":"1.47621282618399","Paridad":"1.05161831471595","Calificación":"A","Monto Emitido":"81920187","Ley":"ARG","Segmento":"Utilities","CALL":"0","Paga":"MEP","Amortización":"Bullet","Vol Total":"232086","ISIN":"AR0674196495"},{"@odata.etag":"","ItemInternalId":"90c3989c-3b95-403c-a3f3-6c0bc0ad0e2e","Link":"link","Empresa":"YPF","Ticker":"YM40O","Name":"ON YPF CL 40","Vto":"46993","Cupon":"0.075","Fq":"T","Vt":"1.01808219178082","Vr":"1","Px":"1.0625","TIR":"0.0550585412979126","Duration":"2.06661650211299","Mduration":"1.95876951014555","Paridad":"1.04362890204521","Calificación":"AAA ","Monto Emitido":"51383412","Ley":"ARG","Segmento":"O&G","CALL":"0","Paga":"MEP","Amortización":"Bullet","Vol Total":"31164","ISIN":"AR0963751125"},{"@odata.etag":"","ItemInternalId":"ec7bc56c-ed67-4fea-84c6-73512e2dff85","Link":"link","Empresa":"Pampa","Ticker":"MGCNO","Name":"ON PAMPA CL 22","Vto":"47030","Cupon":"0.0575","Fq":"S","Vt":"1.00834931506849","Vr":"1","Px":"1.0291780002176","TIR":"0.0485986757278442","Duration":"2.2243117228814","Mduration":"2.12122308979408","Paridad":"1.02065621986136","Calificación":"AA+","Monto Emitido":"83977835","Ley":"ARG","Segmento":"O&G","CALL":"0","Paga":"MEP","Amortización":"Bullet","Vol Total":"121030","ISIN":"AR0765746752"},{"@odata.etag":"","ItemInternalId":"43e8e6ad-90bb-4f5f-9903-b5836c4fe666","Link":"link","Empresa":"YPF","Ticker":"YMCYO","Name":"ON YPF CL 32","Vto":"47036","Cupon":"0.065","Fq":"T","Vt":"1.0083698630137","Vr":"1","Px":"1.036","TIR":"0.0535721349716187","Duration":"2.20582139136277","Mduration":"2.09365957787237","Paridad":"1.02740079607667","Calificación":"AAA ","Monto Emitido":"125000000","Ley":"ARG","Segmento":"O&G","CALL":"0","Paga":"MEP","Amortización":"Bullet","Vol Total":"33281","ISIN":"AR0417757066"},{"@odata.etag":"","ItemInternalId":"56973e6c-d963-4e36-a0bf-81ce4e4ed087","Link":"link","Empresa":"YPF","Ticker":"YMCZO","Name":"ON YPF CL XXXIII","Vto":"47036","Cupon":"0.07","Fq":"S","Vt":"1.00901369863014","Vr":"1","Px":"1.01988306828812","TIR":"0.0659721994400025","Duration":"2.21313105989807","Mduration":"2.07616208101929","Paridad":"1.01077227164779","Calificación":"AAA ","Monto Emitido":"25000000","Ley":"ARG","Segmento":"O&G","CALL":"0","Paga":"CABLE","Amortización":"Bullet","Vol Total":"#N/D","ISIN":"AR0079616063"},{"@odata.etag":"","ItemInternalId":"39341c09-230f-4310-85dc-fa8f2a0e1651","Link":"link","Empresa":"Aluar","Ticker":"LMS7O","Name":"ON ALUAR ALUMINIO ARGENTINO SERIE 7","Vto":"47038","Cupon":"0.07","Fq":"T","Vt":"0.840592356164384","Vr":"1","Px":"0.837066913284735","TIR":"0.0755932092666626","Duration":"1.19997432416598","Mduration":"1.11563955018284","Paridad":"0.995806001739374","Calificación":"AAA","Monto Emitido":"137898136","Ley":"ARG","Segmento":"Industrials","CALL":"0","Paga":"Cable","Amortización":"12 cuotas","Vol Total":"141188","ISIN":"AR0183513875"},{"@odata.etag":"","ItemInternalId":"9310871d-87e4-4e98-8584-95bdfb93fbe3","Link":"link","Empresa":"PCR","Ticker":"PQCRO","Name":"ON PCR CLASE R","Vto":"47048","Cupon":"0.0675","Fq":"S","Vt":"1.00647260273973","Vr":"1","Px":"0.9975","TIR":"0.0727732610702515","Duration":"2.25141723863752","Mduration":"2.09868880996474","Paridad":"0.991085099867297","Calificación":"A+","Monto Emitido":"46018072","Ley":"ARG","Segmento":"O&G","CALL":"0","Paga":"MEP","Amortización":"Bullet","Vol Total":"414","ISIN":"AR0530125704"},{"@odata.etag":"","ItemInternalId":"6759163a-ce2a-4f1b-b397-af021e742cea","Link":"link","Empresa":"Pan american","Ticker":"PN37O","Name":"ON PAN AMERICAN ENERGY CL 37","Vto":"47070","Cupon":"0.0625","Fq":"S","Vt":"1.00239726027397","Vr":"1","Px":"1.0291780002176","TIR":"0.0514434862136841","Duration":"2.32332107216711","Mduration":"2.20964902310969","Paridad":"1.02671669307667","Calificación":"AAA ","Monto Emitido":"74172648","Ley":"ARG","Segmento":"O&G","CALL":"0","Paga":"MEP","Amortización":"Bullet","Vol Total":"14562","ISIN":"AR0098578880"},{"@odata.etag":"","ItemInternalId":"ad87aeb4-7c1d-4023-a0d6-3af1c15bfb3f","Link":"link","Empresa":"Telecom","Ticker":"TLCOO","Name":"ON.TELECOM ARGENTINA C.  23","Vto":"47085","Cupon":"0.07","Fq":"S","Vt":"1","Vr":"1","Px":"1.0695","TIR":"0.0138409090042114","Duration":"2.39317108609316","Mduration":"2.36049962557115","Paridad":"0","Calificación":"AA+","Monto Emitido":"75247975","Ley":"ARG","Segmento":"Utilities","CALL":"0","Paga":"MEP","Amortización":"Bullet","Vol Total":"47346","ISIN":"AR0241562484"},{"@odata.etag":"","ItemInternalId":"618a221b-5e17-4386-a2b5-6023ee772701","Link":"link","Empresa":"Scania","Ticker":"SBC2O","Name":"ON SCANIA CREDIT ARG CLASE 2","Vto":"47134","Cupon":"0.0749","Fq":"T","Vt":"1.02688191780822","Vr":"1","Px":"1.044","TIR":"0.0631040620803833","Duration":"1.30148834943662","Mduration":"1.22423419856918","Paridad":"1.01666996165277","Calificación":"A+","Monto Emitido":"40979825","Ley":"ARG","Segmento":"Utilities","CALL":"0","Paga":"MEP","Amortización":"11 cuotas","Vol Total":"28186","ISIN":"AR0318379242"},{"@odata.etag":"","ItemInternalId":"ce932e8f-c2e3-4b26-8e0c-f74173725029","Link":"link","Empresa":"Loma Negra","Ticker":"LOC6O","Name":"ON LOMA NEGRA S.A CL 6","Vto":"47141","Cupon":"0.065","Fq":"S","Vt":"1.02208219178082","Vr":"1","Px":"1.0385","TIR":"0.0590521001815796","Duration":"2.4389727753089","Mduration":"2.30297713860416","Paridad":"1.01606309976947","Calificación":"AAA","Monto Emitido":"60000000","Ley":"ARG","Segmento":"Industrials","CALL":"n/a","Paga":"MEP","Amortización":"Bullet","Vol Total":"147401","ISIN":"AR0204516451"},{"@odata.etag":"","ItemInternalId":"352cfb54-ecae-435f-afde-113e9f0dfc10","Link":"link","Empresa":"Pluspetrol","Ticker":"PLC6O","Name":"ON PLUSPETROL CLASE 6","Vto":"47176","Cupon":"0.065","Fq":"S","Vt":"1.01584931506849","Vr":"1","Px":"1.0395","TIR":"0.0562623357772827","Duration":"2.54060712803142","Mduration":"2.40528043268895","Paridad":"1.02328168615235","Calificación":"A+","Monto Emitido":"167492889","Ley":"ARG","Segmento":"O&G","CALL":"n/a","Paga":"MEP","Amortización":"Bullet","Vol Total":"192676","ISIN":"AR0559091100"},{"@odata.etag":"","ItemInternalId":"92097ac4-9457-46c3-8fbe-abe1f4d9ce9b","Link":"link","Empresa":"YPF","Ticker":"YM42O","Name":"ON YPF CL 42","Vto":"47179","Cupon":"0.07","Fq":"S","Vt":"1.03375342465753","Vr":"1","Px":"1.073","TIR":"0.0538417100906372","Duration":"2.71222847031243","Mduration":"2.57365830593208","Paridad":"1.03796512244249","Calificación":"AAA ","Monto Emitido":"355922807","Ley":"ARG","Segmento":"O&G","CALL":"02/09/27-01/03/28 @101 / 02/03/28-01/03/29 @100","Paga":"MEP","Amortización":"Bullet","Vol Total":"922044","ISIN":"AR0123407162"},{"@odata.etag":"","ItemInternalId":"4081d434-c408-438a-8497-4fba9b08a389","Link":"link","Empresa":"Telecom","Ticker":"TLCUO","Name":"ON.TELECOM ARGENTINA C.  28","Vto":"47182","Cupon":"0.065","Fq":"S","Vt":"1.01495890410959","Vr":"1","Px":"1.03","TIR":"0.05985435962677","Duration":"2.54832795177882","Mduration":"2.40441333154135","Paridad":"1.01481941370188","Calificación":"AA+","Monto Emitido":"81329886","Ley":"ARG","Segmento":"Utilities","CALL":"0","Paga":"MEP","Amortización":"Bullet","Vol Total":"31210","ISIN":"AR0857544677"},{"@odata.etag":"","ItemInternalId":"12a011d8-507f-4918-acb1-af6191dda2c9","Link":"link","Empresa":"Cresud","Ticker":"CS50O","Name":"ON CRESUD CL 50","Vto":"47187","Cupon":"0.0725","Fq":"S","Vt":"1.00814383561644","Vr":"1","Px":"1.064","TIR":"0.0517611360549927","Duration":"2.87234597855895","Mduration":"2.73098698943442","Paridad":"1.05540495553336","Calificación":"AAA","Monto Emitido":"70381079","Ley":"ARG","Segmento":"Real Estate","CALL":"n/a","Paga":"MEP","Amortización":"Bullet","Vol Total":"37446","ISIN":"AR0394353335"},{"@odata.etag":"","ItemInternalId":"4739b708-2060-4d74-9d95-ee7d1f38b4bb","Link":"link","Empresa":"Pampa","Ticker":"MGCTO","Name":"ON PAMPA CL 27","Vto":"47209","Cupon":"0.0549","Fq":"S","Vt":"1.00842301369863","Vr":"1","Px":"1.0075","TIR":"0.0559857034683228","Duration":"2.6554946460952","Mduration":"2.51470700538216","Paridad":"0.999084695920173","Calificación":"AAA","Monto Emitido":"200000000","Ley":"ARG","Segmento":"O&G","CALL":"0","Paga":"MEP","Amortización":"Bullet","Vol Total":"113000","ISIN":"AR0145481872"},{"@odata.etag":"","ItemInternalId":"a30d198c-b1f7-4801-98ff-06a4818693c8","Link":"link","Empresa":"MSU SA","Ticker":"MSSGO","Name":"ON MSU SERIE 15","Vto":"47224","Cupon":"0.085","Fq":"S","Vt":"1.00954794520548","Vr":"1","Px":"1.0295","TIR":"0.0785883188247681","Duration":"2.6040529467798","Mduration":"2.41431591769618","Paridad":"1.01976335536046","Calificación":"A+","Monto Emitido":"34876339","Ley":"ARG","Segmento":"AGRO","CALL":"no","Paga":"MEP","Amortización":"Bullet","Vol Total":"2424","ISIN":"AR0268611834"},{"@odata.etag":"","ItemInternalId":"9c361e68-9038-456f-aa8e-20972e858d71","Link":"link","Empresa":"Vista","Ticker":"VSCPO","Name":"ON VISTA OIL & GAS CL 24","Vto":"47241","Cupon":"0.08","Fq":"S","Vt":"1.0052602739726","Vr":"1","Px":"1.03048175865295","TIR":"0.0684493017196655","Duration":"2.03609974668318","Mduration":"1.90565873683111","Paridad":"1.02508950699969","Calificación":"AAA ","Monto Emitido":"46561789","Ley":"ARG","Segmento":"O&G","CALL":"0","Paga":"CABLE","Amortización":"Amort","Vol Total":"34172","ISIN":"AR0637277028"},{"@odata.etag":"","ItemInternalId":"e1985f1b-9822-462c-ba92-fdc2d99b17d2","Link":"link","Empresa":"Tecpetrol","Ticker":"TTCEO","Name":"ON TECPETROL CL 13","Vto":"47259","Cupon":"0.055","Fq":"S","Vt":"1.00090410958904","Vr":"1","Px":"0.9999","TIR":"0.0561216688156128","Duration":"2.79261742044732","Mduration":"2.64421941420736","Paridad":"0.998996797416035","Calificación":"AAA(arg)","Monto Emitido":"100000000","Ley":"ARG","Segmento":"O&G","CALL":"-","Paga":"MEP","Amortización":"Bullet","Vol Total":"207050","ISIN":""},{"@odata.etag":"","ItemInternalId":"f9945fac-f3bc-4bd7-baa2-c3c15c7f7a69","Link":"link","Empresa":"Oiltanking","Ticker":"OTS6O","Name":"ON OILTANKING EBYTEM SA S6","Vto":"47328","Cupon":"0.0674","Fq":"T","Vt":"1.0217895890411","Vr":"1","Px":"1.033","TIR":"0.0640020322799683","Duration":"2.43619251974586","Mduration":"2.28965025050331","Paridad":"1.01097134975648","Calificación":"AAA","Monto Emitido":"50000000","Ley":"ARG","Segmento":"O&G","CALL":"no","Paga":"MEP","Amortización":"Bullet","Vol Total":"36222","ISIN":"AR0110435994"},{"@odata.etag":"","ItemInternalId":"5bdf5f9c-d8b1-4a7c-bcbf-d27dee601ee7","Link":"link","Empresa":"CEPU","Ticker":"NPCCO","Name":"ON.CENTRAL PUERTO SA CL C","Vto":"47355","Cupon":"0.08","Fq":"S","Vt":"1.01994520547945","Vr":"1","Px":"1.04059869036483","TIR":"0.073890175819397","Duration":"2.87990403594385","Mduration":"2.68174912182843","Paridad":"1.02024960240454","Calificación":"AA-","Monto Emitido":"89067309","Ley":"ARG","Segmento":"Utilities","CALL":"-","Paga":"CABLE","Amortización":"Bullet","Vol Total":"164844","ISIN":"AR0630055561"},{"@odata.etag":"","ItemInternalId":"4ee7c34d-bfa6-485e-a9df-e71eb7d24a4f","Link":"link","Empresa":"Pan american","Ticker":"PN41O","Name":"ON PAN AMERICAN ENERGY CL 41","Vto":"47357","Cupon":"0.075","Fq":"S","Vt":"1.01828767123288","Vr":"1","Px":"1.0845","TIR":"0.0532417917251587","Duration":"2.91225716769442","Mduration":"2.76504140889082","Paridad":"1.06502320575772","Calificación":"AAA ","Monto Emitido":"85939129","Ley":"ARG","Segmento":"O&G","CALL":"0","Paga":"MEP","Amortización":"Bullet","Vol Total":"65766","ISIN":"AR0299198264"},{"@odata.etag":"","ItemInternalId":"fe8ab058-53fb-4263-b807-a24f06b82de0","Link":"link","Empresa":"Pan american","Ticker":"PN35O","Name":"ON PAN AMERICAN ENERGY CL 35","Vto":"47388","Cupon":"0.07","Fq":"S","Vt":"1.01169863013699","Vr":"1","Px":"1.0595","TIR":"0.0548532629013061","Duration":"3.01261971963127","Mduration":"2.8559609431792","Paridad":"1.04724862566686","Calificación":"AAA ","Monto Emitido":"176944529","Ley":"ARG","Segmento":"O&G","CALL":"0","Paga":"MEP","Amortización":"Bullet","Vol Total":"347895","ISIN":"AR0623274765"},{"@odata.etag":"","ItemInternalId":"040ec0bc-97c2-4582-aec2-90c2c2da0dbb","Link":"link","Empresa":"Irsa","Ticker":"IRCOO","Name":"ON IRSA CL 23","Vto":"47414","Cupon":"0.0725","Fq":"S","Vt":"1.00675342465753","Vr":"1","Px":"1.06936827331085","TIR":"0.0527831697463989","Duration":"3.08159273971926","Mduration":"2.92709156859107","Paridad":"1.06219482061818","Calificación":"AA+ ","Monto Emitido":"51467822","Ley":"ARG","Segmento":"Real Estate","CALL":"0","Paga":"MEP","Amortización":"Bullet","Vol Total":"81811","ISIN":"AR0084572384"},{"@odata.etag":"","ItemInternalId":"713bb2c4-11ed-45d7-82ec-bf3a16ab12c2","Link":"link","Empresa":"Tecpetrol","Ticker":"TTC9O","Name":"ON TECPETROL CLASE 9","Vto":"47415","Cupon":"0.068","Fq":"S","Vt":"1.00614794520548","Vr":"1","Px":"1.04836606462844","TIR":"0.0549908018112183","Duration":"3.09459962508261","Mduration":"2.93329536122","Paridad":"1.04196015071555","Calificación":"AAA","Monto Emitido":"80541942","Ley":"ARG","Segmento":"O&G","CALL":"-","Paga":"MEP","Amortización":"Bullet","Vol Total":"86383","ISIN":"AR0482976963"},{"@odata.etag":"","ItemInternalId":"0c607156-f466-4102-95c9-b09275f20950","Link":"link","Empresa":"Profertil","Ticker":"PFC3O","Name":"ON PROFERTIL CL 3","Vto":"47430","Cupon":"0.0575","Fq":"S","Vt":"1.00299315068493","Vr":"1","Px":"0.9984","TIR":"0.0598397970199585","Duration":"3.17307668608827","Mduration":"2.99392105770162","Paridad":"0.995420556280175","Calificación":"Bullet","Monto Emitido":"70000000","Ley":"ARG","Segmento":"AGRO","CALL":"AAA(arg)","Paga":"MEP","Amortización":"0","Vol Total":"93300","ISIN":"AR0645095644"},{"@odata.etag":"","ItemInternalId":"037bc20f-e33a-40a8-ab2a-74653cba6f5b","Link":"link","Empresa":"Pluspetrol","Ticker":"PLC2O","Name":"ON PLUSPETROL C2 USD 7,5%","Vto":"47510","Cupon":"0.075","Fq":"S","Vt":"1.00616438356164","Vr":"1","Px":"1.0605766510717","TIR":"0.0591496229171753","Duration":"3.27363898191692","Mduration":"3.09081824803984","Paridad":"1.05407890440074","Calificación":"A+","Monto Emitido":"123020337","Ley":"ARG","Segmento":"O&G","CALL":"0","Paga":"MEP","Amortización":"Bullet","Vol Total":"47095","ISIN":"AR0036431960"},{"@odata.etag":"","ItemInternalId":"894ebc07-e554-4745-ab8f-fe1fada8e5f8","Link":"link","Empresa":"Oleoductos del valle","Ticker":"OLC7O","Name":"ON OLEDUCTOS DEL VALLE CLASE 7","Vto":"47537","Cupon":"0.069","Fq":"s","Vt":"1.01758082191781","Vr":"1","Px":"1.047","TIR":"0.0430602312088013","Duration":"3.35802189017615","Mduration":"3.21939403852502","Paridad":"1.02891090068575","Calificación":"AAA ","Monto Emitido":"110000000","Ley":"ARG","Segmento":"O&G","CALL":"0","Paga":"MEP","Amortización":"Bullet","Vol Total":"25267","ISIN":"AR0888142434"},{"@odata.etag":"","ItemInternalId":"87a9b4d0-7c1b-44b8-9993-2608a8a4339a","Link":"link","Empresa":"Vista","Ticker":"VSCUO","Name":"ON VISTA OIL & GAS CL 28","Vto":"47549","Cupon":"0.075","Fq":"S","Vt":"1.01664383561644","Vr":"1","Px":"1.04156220767072","TIR":"0.0685095357894898","Duration":"3.31647797285859","Mduration":"3.10383563438032","Paridad":"1.02451042457674","Calificación":"AAA ","Monto Emitido":"92413570","Ley":"ARG","Segmento":"O&G","CALL":"N/A","Paga":"CABLE","Amortización":"Bullet","Vol Total":"235738","ISIN":"AR0707929003"},{"@odata.etag":"","ItemInternalId":"659481d3-06cb-4bfe-a346-aa6438613c33","Link":"link","Empresa":"YPF","Ticker":"YM43O","Name":"ON YPF CL 43","Vto":"47587","Cupon":"0.055","Fq":"S","Vt":"1.00647945205479","Vr":"1","Px":"0.996383853769992","TIR":"0.0586512422561646","Duration":"3.53408127193454","Mduration":"3.33828661496001","Paridad":"0.989969394542341","Calificación":"AAA ","Monto Emitido":"122146525","Ley":"ARG","Segmento":"O&G","CALL":"0","Paga":"MEP","Amortización":"Bullet","Vol Total":"31583","ISIN":"AR0156884063"},{"@odata.etag":"","ItemInternalId":"33702549-1963-423b-aa86-cfbf400707ac","Link":"link","Empresa":"Cresud","Ticker":"CS53O","Name":"ON CRESUD CL 53","Vto":"47603","Cupon":"0.0625","Fq":"S","Vt":"1.00462328767123","Vr":"1","Px":"1.006","TIR":"0.0629629278182983","Duration":"3.53449544372726","Mduration":"0","Paridad":"0","Calificación":"AAA","Monto Emitido":"22998047","Ley":"ARG","Segmento":"Real Estate","CALL":"n/a","Paga":"MEP","Amortización":"Bullet","Vol Total":"15430","ISIN":"AR0092809794"},{"@odata.etag":"","ItemInternalId":"27a912ea-3498-4097-b2f9-e83e7df69563","Link":"link","Empresa":"YPF","Ticker":"YM39O","Name":"ON YPF CL 39","Vto":"47686","Cupon":"0.0875","Fq":"s","Vt":"1.02996575342466","Vr":"1","Px":"1.08492048643592","TIR":"0.0732044553756714","Duration":"3.49447411054312","Mduration":"3.25611219096168","Paridad":"1.05335588375491","Calificación":"AAA ","Monto Emitido":"224801688","Ley":"ARG","Segmento":"O&G","CALL":"0","Paga":"CABLE","Amortización":"Bullet","Vol Total":"178032","ISIN":"AR0081455617"},{"@odata.etag":"","ItemInternalId":"d7e7698b-df5c-4e34-b13a-006c6ef332fd","Link":"link","Empresa":"Vista","Ticker":"VSCRO","Name":"ON VISTA OIL & GAS CL 26","Vto":"48131","Cupon":"0.0765","Fq":"S","Vt":"1.00985068493151","Vr":"1","Px":"1.08953318463714","TIR":"0.0564302587509155","Duration":"3.79239569210441","Mduration":"3.58982115543377","Paridad":"1.0789052291538","Calificación":"AAA ","Monto Emitido":"150000000","Ley":"ARG","Segmento":"O&G","CALL":"0","Paga":"MEP","Amortización":"Bullet","Vol Total":"256251","ISIN":"AR0138120560"},{"@odata.etag":"","ItemInternalId":"8fd89f45-ade1-4565-bf7b-dc1a1c2b559f","Link":"link","Empresa":"Pan american","Ticker":"PN36O","Name":"ON PAN AMERICAN ENERGY CL 36","Vto":"48165","Cupon":"0.0725","Fq":"S","Vt":"1.00278082191781","Vr":"1","Px":"1.062","TIR":"0.0605238485336304","Duration":"4.62841988806677","Mduration":"4.3642770452229","Paridad":"1.05905495676407","Calificación":"AAA ","Monto Emitido":"78100553","Ley":"ARG","Segmento":"O&G","CALL":"0","Paga":"MEP","Amortización":"Bullet","Vol Total":"199004","ISIN":"AR0677571967"},{"@odata.etag":"","ItemInternalId":"29b0bc84-a62a-4abe-af07-ba626eb54f9a","Link":"","Empresa":"","Ticker":"","Name":"","Vto":"","Cupon":"","Fq":"","Vt":"","Vr":"","Px":"","TIR":"","Duration":"","Mduration":"0","Paridad":"#¡DIV/0!","Calificación":"","Monto Emitido":"","Ley":"","Segmento":"","CALL":"","Paga":"","Amortización":"","Vol Total":"","ISIN":""}],"ny":[{"@odata.etag":"","ItemInternalId":"a5851fa4-27fd-4d73-b516-fc4bebda519c","Link":"link","Empresa":"Banco Galicia","TiCKER BBG":"GALIAR 26","Ticker":"BYC2O","Name":"ON BANCO GALICIA CL 2","Vto":"46222","Cupon":"0.07962","Fq":"S","Vt":"1.02792153424658","Vr":"1","Px":"0.92414702525725","TIR":"1.21902094841003","Duration":"0.15","Mduration":"0.0675973789735863","Paridad":"0.899044328256643","Calificación":"CCC","Monto Emitido":"250000000","Ley":"NY","Segmento":"FINANCIALS","CALL":"Yes","Paga":"CABLE","Amortización":"Bullet","volumen total":"0","ISIN":"USP0R66CAA64"},{"@odata.etag":"","ItemInternalId":"c387bc28-b8e5-460d-b420-b531cd27c41f","Link":"link","Empresa":"Banco Macro","TiCKER BBG":"BMAAR 26","Ticker":"BACAO","Name":"ON BANCO MACRO CL A","Vto":"46330","Cupon":"0.0675","Fq":"S","Vt":"1.00425342465753","Vr":"1","Px":"0.9208","TIR":"0.299933953285217","Duration":"0.447222222222222","Mduration":"0.344034572750403","Paridad":"0.916900034783558","Calificación":"CCC+","Monto Emitido":"400000000","Ley":"NY","Segmento":"FINANCIALS","CALL":"Yes","Paga":"CABLE","Amortización":"Bullet","volumen total":"0","ISIN":"USP1047VAF42"},{"@odata.etag":"","ItemInternalId":"e7848308-6d34-45b1-9b3d-39fe30b51f75","Link":"link","Empresa":"PAE","TiCKER BBG":"PANAME 27","Ticker":"PNDCO","Name":"ON.PAN AMERCIAN ENERGY C12","Vto":"46507","Cupon":"0.09125","Fq":"S","Vt":"0.4027","Vr":"0.4","Px":"0.410431073876618","TIR":"0.0622856092453003","Duration":"0.676856488741729","Mduration":"0.63716996902801","Paridad":"1.0191980975332","Calificación":"AAA ","Monto Emitido":"300000000","Ley":"NY","Segmento":"O&G","CALL":"0","Paga":"CABLE","Amortización":"5 Cuotas","volumen total":"886000","ISIN":"USE7S78BAB82"},{"@odata.etag":"","ItemInternalId":"74064a0a-bcd5-4ca3-a654-53f0f426f28d","Link":"link","Empresa":"YPF","TiCKER BBG":"YPFDAR 27","Ticker":"YCAMO","Name":"ON YPF CLASE 53","Vto":"46589","Cupon":"0.0695","Fq":"S","Vt":"1","Vr":"0","Px":"1.04927034611787","TIR":"0.0471509981155395","Duration":"1.11728094874749","Mduration":"1.06697214705249","Paridad":"1.0246862970674","Calificación":"B2","Monto Emitido":"809303000","Ley":"NY","Segmento":"O&G","CALL":"Yes","Paga":"CABLE","Amortización":"Bullet","volumen total":"20000","ISIN":"USP989MJBL47"},{"@odata.etag":"","ItemInternalId":"566334d4-b08a-4fda-8cd0-facefc64d289","Link":"link","Empresa":"Irsa","TiCKER BBG":"IRSAAR 28","Ticker":"IRCFO","Name":"ON IRSA CL 14","Vto":"46926","Cupon":"0.0875","Fq":"S","Vt":"0.65","Vr":"0.674308219178082","Px":"0.683037418147802","TIR":"0.0756290292739868","Duration":"1.18003649998165","Mduration":"1.09706643077319","Paridad":"1.01294541386483","Calificación":"AA+ ","Monto Emitido":"171202815","Ley":"NY","Segmento":"Real Estate","CALL":"","Paga":"CABLE","Amortización":"5 cuotas","volumen total":"61545","ISIN":"USP58809BH95"},{"@odata.etag":"","ItemInternalId":"006db546-037f-4af0-a6c9-a8350bd94842","Link":"link","Empresa":"Banco Galicia","TiCKER BBG":"GALIAR 28","Ticker":"BYCHO","Name":"ON BANCO GALICIA CL 16","Vto":"47036","Cupon":"0.0775","Fq":"S","Vt":"1","Vr":"1.00997945205479","Px":"1.04053421825699","TIR":"0.0643703985214233","Duration":"2.22942283433113","Mduration":"2.09459304526709","Paridad":"1.03025285924385","Calificación":"CCC","Monto Emitido":"325000000","Ley":"NY","Segmento":"FINANCIALS","CALL":"Yes","Paga":"CABLE","Amortización":"Bullet","volumen total":"169218","ISIN":"USP0R66CAB48"},{"@odata.etag":"","ItemInternalId":"bcf94e62-b803-4b23-b1c7-c5eafcbd8bea","Link":"link","Empresa":"Banco Macro","TiCKER BBG":"BMAAR 29","Ticker":"BACGO","Name":"ON BANCO MACRO CL G","Vto":"47292","Cupon":"0.08","Fq":"S","Vt":"1","Vr":"1.03397260273973","Px":"1.05794200187091","TIR":"0.0709706544876099","Duration":"2.74971115107318","Mduration":"2.56749439356836","Paridad":"1.02318185130599","Calificación":"CCC+","Monto Emitido":"400000000","Ley":"NY","Segmento":"FINANCIALS","CALL":"Yes","Paga":"CABLE","Amortización":"Bullet","volumen total":"149000","ISIN":"USP1047VAL10"},{"@odata.etag":"","ItemInternalId":"bbebf319-cb09-43c7-bd48-f55939542640","Link":"link","Empresa":"YPF","TiCKER BBG":"YPFDAR 29","Ticker":"YMCIO","Name":"ON YPF CLASE 17","Vto":"47299","Cupon":"Step Up","Fq":"S","Vt":"1.03649315068493","Vr":"1","Px":"1.07375062561201","TIR":"0.0654496622085571","Duration":"1.47661663152213","Mduration":"1.38590933377488","Paridad":"1.03594570297205","Calificación":"B2","Monto Emitido":"747833257","Ley":"NY","Segmento":"O&G","CALL":"Yes","Paga":"CABLE","Amortización":"7 cuotas","volumen total":"201131","ISIN":"USP989MJBS99"},{"@odata.etag":"","ItemInternalId":"5fa50e8f-48c2-4be8-a197-95df97f23ebd","Link":"link","Empresa":"Edenor","TiCKER BBG":"EDNAR 30","Ticker":"DNC7O","Name":"ON EDENOR CL7","Vto":"47780","Cupon":"0.0975","Fq":"S","Vt":"1.00881506849315","Vr":"1","Px":"1.03549124143184","TIR":"0.0895118284225464","Duration":"2.85087671077611","Mduration":"2.61665512608868","Paridad":"1.03549124143184","Calificación":"B-","Monto Emitido":"385000000","Ley":"NY","Segmento":"Utilities","CALL":"-","Paga":"CABLE","Amortización":"3 cuotas","volumen total":"115600","ISIN":"USP3710FAU86"},{"@odata.etag":"","ItemInternalId":"e8b5a9e8-5557-4097-aa1b-ac671b69864e","Link":"link","Empresa":"Tecpetrol","TiCKER BBG":"TECPETROL 30","Ticker":"TTCDO","Name":"ON.TECPETROL CLASE XII","Vto":"47790","Cupon":"0.07625","Fq":"S","Vt":"1.00501369863014","Vr":"1","Px":"1.03","TIR":"0.0706381464004517","Duration":"3.89606841855241","Mduration":"3.63901513471308","Paridad":"1.0248616525366","Calificación":"B1","Monto Emitido":"750000000","Ley":"NY","Segmento":"O&G","CALL":"YES","Paga":"CABLE","Amortización":"Bullet","volumen total":"246000","ISIN":"USP90187AT55"},{"@odata.etag":"","ItemInternalId":"b64242b0-81c4-4464-a839-412b0aab2af5","Link":"link","Empresa":"Pluspetrol","TiCKER BBG":"PLUSPE 32","Ticker":"PLC5O","Name":"ON PLUSPETROL Clase 5","Vto":"47986","Cupon":"0.08125","Fq":"S","Vt":"1","Vr":"1","Px":"1.03878598629094","TIR":"0.0738488912582398","Duration":"4.62614579222663","Mduration":"4.30800444074224","Paridad":"1.03878598629094","Calificación":"BB","Monto Emitido":"500000000","Ley":"NY","Segmento":"O&G","CALL":"yes","Paga":"CABLE","Amortización":"Bullet","volumen total":"164000","ISIN":"USP7924AAC29"},{"@odata.etag":"","ItemInternalId":"fc2ad3cf-2d0a-491c-9f2d-a0636fa397cc","Link":"link","Empresa":"Telecom","TiCKER BBG":"TECOAR 31","Ticker":"TLCMO","Name":"ON TELECOM ARGENTINA C27","Vto":"48047","Cupon":"0.095","Fq":"S","Vt":"1.00052054794521","Vr":"1","Px":"1.10441192470895","TIR":"0.0688977003097534","Duration":"3.7978999738618","Mduration":"3.55309958358149","Paridad":"1.10383732445787","Calificación":"B/RR3","Monto Emitido":"817000000","Ley":"NY","Segmento":"Utilities","CALL":"no","Paga":"CABLE","Amortización":"3 cuotas","volumen total":"508000","ISIN":"USP9028NBT74"},{"@odata.etag":"","ItemInternalId":"8f04cbac-430d-4218-90fa-21fb39ab5b22","Link":"link","Empresa":"Pampa","TiCKER BBG":"PAMPAR 31","Ticker":"MGCMO","Name":"ON PAMPA ENERGIA CL 21","Vto":"48101","Cupon":"0.0795","Fq":"S","Vt":"1.01698904109589","Vr":"1","Px":"1.0745","TIR":"0.0636681127548218","Duration":"3.74136579571605","Mduration":"3.51741840415446","Paridad":"1.05655022481082","Calificación":"AAA ","Monto Emitido":"410000000","Ley":"NY","Segmento":"O&G","CALL":"Yes","Paga":"CABLE","Amortización":"Bullet","volumen total":"174000","ISIN":"USP7464EAS56"},{"@odata.etag":"","ItemInternalId":"d4e94867-61b4-411c-9931-b8d1c180cd41","Link":"link","Empresa":"YPF","TiCKER BBG":"YPFDAR 31","Ticker":"YMCXO","Name":"ON YPF CLASE 31","Vto":"48102","Cupon":"0.0875","Fq":"S","Vt":"1.01845890410959","Vr":"1","Px":"1.075","TIR":"0.074272141456604","Duration":"3.94819123447218","Mduration":"3.67522444463545","Paridad":"1.055516325364","Calificación":"B2","Monto Emitido":"500000000","Ley":"NY","Segmento":"O&G","CALL":"Yes","Paga":"CABLE","Amortización":"3 cuotas","volumen total":"772241","ISIN":"USP989MJBV29"},{"@odata.etag":"","ItemInternalId":"85bcda54-0cc7-4437-9efc-e13c5d310a52","Link":"link","Empresa":"PAE","TiCKER BBG":"PANAME 32","Ticker":"PNXCO","Name":"ON.PAN AMERCIAN ENERGY C31","Vto":"48334","Cupon":"0.085","Fq":"S","Vt":"1","Vr":"1.00628767123288","Px":"1.08684752104771","TIR":"0.0665207815170288","Duration":"4.18710911710757","Mduration":"3.92595173921673","Paridad":"1.08005648098235","Calificación":"AAA ","Monto Emitido":"400000000","Ley":"NY","Segmento":"O&G","CALL":"0","Paga":"CABLE","Amortización":"3 Cuotas","volumen total":"179000","ISIN":"USE7S78BAC65"},{"@odata.etag":"","ItemInternalId":"e691de60-86fd-49d9-a222-7d69bd5d447a","Link":"link","Empresa":"Pluspetrol","TiCKER BBG":"PLUSPETROL 32","Ticker":"PLC4O","Name":"ON PLUSPETROL C4","Vto":"48364","Cupon":"0.085","Fq":"S","Vt":"1.04145205479452","Vr":"1","Px":"1.092","TIR":"0.075763897895813","Duration":"4.74257891484786","Mduration":"4.40856857543213","Paridad":"1.04853602714861","Calificación":"BB","Monto Emitido":"650000000","Ley":"NY","Segmento":"O&G","CALL":"yes","Paga":"CABLE","Amortización":"Bullet","volumen total":"427000","ISIN":"USP7924AAA62"},{"@odata.etag":"","ItemInternalId":"3e53d9c3-4f7b-4073-9c5f-44cf0eda520d","Link":"link","Empresa":"YPF LUZ","TiCKER BBG":"YPFLUZ32","Ticker":"YFCJO","Name":"ON YPF ENERGIA ELECTRICA C18","Vto":"48503","Cupon":"0.07875","Fq":"S","Vt":"1.00884589041096","Vr":"1","Px":"1.03144527595884","TIR":"0.0736797094345093","Duration":"4.47093984475296","Mduration":"4.164128096551","Paridad":"1.02240122675097","Calificación":"B2","Monto Emitido":"420000000","Ley":"NY","Segmento":"O&G","CALL":"Yes","Paga":"CABLE","Amortización":"3 cuotas","volumen total":"289000","ISIN":"USP9897PAS31"},{"@odata.etag":"","ItemInternalId":"44973968-574c-4809-889c-b3895b320a11","Link":"link","Empresa":"Tecpetrol","TiCKER BBG":"TECPETROL 33","Ticker":"TTCAO","Name":"ON.TECPETROL CLASE X","Vto":"48601","Cupon":"0.07625","Fq":"S","Vt":"1","Vr":"1.02611301369863","Px":"1.06179607109448","TIR":"0.070149188041687","Duration":"4.99625721375343","Mduration":"4.66874831059425","Paridad":"1.03477497792103","Calificación":"AAA","Monto Emitido":"400000000","Ley":"NY","Segmento":"O&G","CALL":"-","Paga":"CABLE","Amortización":"3 cuotas (33,33y34)","volumen total":"12000","ISIN":"USP90187AR99"},{"@odata.etag":"","ItemInternalId":"e00d3121-1dbd-42a2-9f3c-0ffe6200011a","Link":"link","Empresa":"Telecom","TiCKER BBG":"TECOAR 33","Ticker":"TLCPO","Name":"ON TELECOM ARGENTINA C24","Vto":"48727","Cupon":"0.0925","Fq":"S","Vt":"1","Vr":"1.04561643835616","Px":"1.11611163094331","TIR":"0.0799350214004516","Duration":"4.93977284844883","Mduration":"4.57413895332607","Paridad":"1.06741974399138","Calificación":"B/RR3","Monto Emitido":"800000000","Ley":"NY","Segmento":"Utilities","CALL":"no","Paga":"CABLE","Amortización":"2 cuotas","volumen total":"581328","ISIN":"USP9028NCA74"},{"@odata.etag":"","ItemInternalId":"eda1fe02-89b8-4148-a42f-dcaaa7433474","Link":"link","Empresa":"Vista","TiCKER BBG":"VISTAA 33","Ticker":"VSCVO","Name":"ON VISTA OIL & GAS CL 29","Vto":"48740","Cupon":"0.085","Fq":"S","Vt":"1","Vr":"1.03912328767123","Px":"1.10609291698401","TIR":"0.0723951101303101","Duration":"4.71534077140758","Mduration":"4.39701815764024","Paridad":"1.06444820369954","Calificación":"AAA ","Monto Emitido":"500000000","Ley":"NY","Segmento":"O&G","CALL":"0","Paga":"CABLE","Amortización":"3 cuotas","volumen total":"750000","ISIN":"USP9659RAB44"},{"@odata.etag":"","ItemInternalId":"1309a4e4-669c-4171-b545-00d5171340f0","Link":"link","Empresa":"Arcor","TiCKER BBG":"ARCOR 33","Ticker":"RC1CO","Name":"ON ARCOR CLASE 1","Vto":"48791","Cupon":"0.076","Fq":"S","Vt":"1.02415342465753","Vr":"1","Px":"1.05808377760853","TIR":"0.0798297262191772","Duration":"5.05387982202954","Mduration":"4.68025624718145","Paridad":"1.05808377760853","Calificación":"CCC+","Monto Emitido":"350000000","Ley":"NY","Segmento":"Consumer","CALL":"Yes","Paga":"CABLE","Amortización":"Bullet","volumen total":"32000","ISIN":"USP04559BE29"},{"@odata.etag":"","ItemInternalId":"69572ec9-0088-4e63-a22c-92115bd789fc","Link":"link","Empresa":"YPF","TiCKER BBG":"YPFDAR 34","Ticker":"YM34O","Name":"ON YPF CLASE 34","Vto":"48961","Cupon":"0.0825","Fq":"S","Vt":"1.02938356164384","Vr":"1","Px":"1.07065759982592","TIR":"0.0763310861587525","Duration":"5.5224054517161","Mduration":"5.13076833209812","Paridad":"1.04009587846553","Calificación":"B2","Monto Emitido":"1100000000","Ley":"NY","Segmento":"O&G","CALL":"Yes","Paga":"CABLE","Amortización":"3 cuotas","volumen total":"1484984","ISIN":"USP989MJBY67"},{"@odata.etag":"","ItemInternalId":"13143376-7a0b-4fb1-8289-f6b4aa61c107","Link":"link","Empresa":"Pampa","TiCKER BBG":"PAMPAR 34","Ticker":"MGCOO","Name":"ON PAMPA ENERGIA CL 23","Vto":"49294","Cupon":"0.07875","Fq":"S","Vt":"1","Vr":"1.03495205479452","Px":"1.066131898971","TIR":"0.0738564920425415","Duration":"6.32250155703316","Mduration":"5.88765966764085","Paridad":"1.03012684890284","Calificación":"AAA ","Monto Emitido":"700000000","Ley":"NY","Segmento":"O&G","CALL":"Yes","Paga":"CABLE","Amortización":"Bullet","volumen total":"166000","ISIN":"USP7464EAT30"},{"@odata.etag":"","ItemInternalId":"f147e58e-aa38-48be-90b0-eadfb4e12e6f","Link":"link","Empresa":"Vista","TiCKER BBG":"VISTAA 35","Ticker":"VSCTO","Name":"ON VISTA OIL & GAS CL 27","Vto":"49653","Cupon":"0.07625","Fq":"S","Vt":"1","Vr":"1.03509589041096","Px":"1.063","TIR":"0.0730749082565308","Duration":"6.24836606456037","Mduration":"5.82286102907052","Paridad":"1.02695799475927","Calificación":"AAA ","Monto Emitido":"600000000","Ley":"NY","Segmento":"O&G","CALL":"0","Paga":"CABLE","Amortización":"3 cuotas","volumen total":"230000","ISIN":"USP9659RAA60"},{"@odata.etag":"","ItemInternalId":"97a8b86d-1513-4f75-a487-b7ae9e524201","Link":"link","Empresa":"Pampa","TiCKER BBG":"PAMPAR 37","Ticker":"MGCRO","Name":"ON PAMPA ENERGIA CL 26","Vto":"50358","Cupon":"0.0775","Fq":"S","Vt":"1.0027602739726","Vr":"1","Px":"1.01726928517028","TIR":"0.0757946729660034","Duration":"7.94840004027611","Mduration":"7.38839877163743","Paridad":"1.01446907259319","Calificación":"B-","Monto Emitido":"450000000","Ley":"NY","Segmento":"O&G","CALL":"Yes","Paga":"CABLE","Amortización":"Bullet","volumen total":"0","ISIN":"USP7464EAY25"},{"@odata.etag":"","ItemInternalId":"af3ec628-be25-4db7-abac-d9da69871f0d","Link":"link","Empresa":"Vista","TiCKER BBG":"VISTAA 38","Ticker":"VSCXO","Name":"ON VISTA OIL & GAS CL 31","Vto":"50503","Cupon":"0.07875","Fq":"S","Vt":"1.01057191780822","Vr":"1","Px":"1.0385","TIR":"0.0762541341781616","Duration":"7.56400190128267","Mduration":"7.02808162224493","Paridad":"1.02763591754296","Calificación":"BB-","Monto Emitido":"500000000","Ley":"NY","Segmento":"O&G","CALL":"0","Paga":"CABLE","Amortización":"3 cuotas","volumen total":"2225000","ISIN":"US92841RAC43"}]}